{"id":62,"name_zh":"串謀參與暴動","name_en":"","content_zh":"第245章 《公安條例》第19條：\n如任何參與被定為非法集結的集結的人破壞社會安寧，該集結即屬暴動，而集結的人即屬集結暴動\n\n《刑事罪行條例》第159A條：\n(1) 除本部條文另有規定外，如任何人與任何其他人達成作出某項行為的協議，而該項協議如按照他們的意圖得以落實，即出現以下的情況 ——該項行為必會構成或涉及協議的一方或多於一方犯一項或多於一項罪行","content_en":"","defendants":[{"person":{"id":"c9295502-62b3-4b99-90b2-60e669659715","initial_zh":"胡","initial_en":"","hide_name":true,"gender":"male","image_url":null,"case_person":[{"arrest_age":null,"occupation":{"type_zh":"學生","type_en":"學生"},"status":{"id":5,"type_zh":"當庭釋放","type_en":"當庭釋放"}}]},"case":{"type":"original","progress":{"id":9,"type_zh":"上訴","type_en":"上訴"}},"progress":{"id":3,"type_zh":"上訴","type_en":"上訴","fill":"#f6d973","contrast":"#000000","i18nText":"case.appeal"},"id":"c9295502-62b3-4b99-90b2-60e669659715"},{"person":{"id":"fb560a2c-87a6-488d-ba6c-cd9f18ccb608","initial_zh":"陳","initial_en":"","hide_name":true,"gender":"male","image_url":null,"case_person":[{"arrest_age":null,"occupation":{"type_zh":"學生","type_en":"學生"},"status":{"id":5,"type_zh":"當庭釋放","type_en":"當庭釋放"}}]},"case":{"type":"original","progress":{"id":9,"type_zh":"上訴","type_en":"上訴"}},"progress":{"id":3,"type_zh":"上訴","type_en":"上訴","fill":"#f6d973","contrast":"#000000","i18nText":"case.appeal"},"id":"fb560a2c-87a6-488d-ba6c-cd9f18ccb608"},{"person":{"id":"2f79bcad-62c7-4fdc-acff-575eb141c3a4","initial_zh":"李","initial_en":"","hide_name":true,"gender":"female","image_url":null,"case_person":[{"arrest_age":null,"occupation":{"type_zh":"文員","type_en":"文員"},"status":{"id":5,"type_zh":"當庭釋放","type_en":"當庭釋放"}}]},"case":{"type":"original","progress":{"id":9,"type_zh":"上訴","type_en":"上訴"}},"progress":{"id":3,"type_zh":"上訴","type_en":"上訴","fill":"#f6d973","contrast":"#000000","i18nText":"case.appeal"},"id":"2f79bcad-62c7-4fdc-acff-575eb141c3a4"},{"person":{"id":"e85a1c26-dfbe-4613-b435-1150a07bf851","initial_zh":"沈","initial_en":"","hide_name":true,"gender":"male","image_url":null,"case_person":[{"arrest_age":null,"occupation":{"type_zh":"無業","type_en":"無業"},"status":{"id":5,"type_zh":"當庭釋放","type_en":"當庭釋放"}}]},"case":{"type":"original","progress":{"id":9,"type_zh":"上訴","type_en":"上訴"}},"progress":{"id":3,"type_zh":"上訴","type_en":"上訴","fill":"#f6d973","contrast":"#000000","i18nText":"case.appeal"},"id":"e85a1c26-dfbe-4613-b435-1150a07bf851"},{"person":{"id":"b5fae22b-ec6b-411c-8e09-760494c2d549","initial_zh":"林","initial_en":"","hide_name":true,"gender":"male","image_url":null,"case_person":[{"arrest_age":null,"occupation":{"type_zh":"學生","type_en":"學生"},"status":{"id":1,"type_zh":"保釋","type_en":"保釋"}},{"arrest_age":null,"occupation":{"type_zh":"學生","type_en":"學生"},"status":{"id":2,"type_zh":"還柙","type_en":"還柙"}}]},"case":{"type":"original","progress":{"id":1,"type_zh":"提堂","type_en":"提堂"}},"progress":{"id":1,"type_zh":"提堂","type_en":"提堂","fill":"#0c2c96","contrast":"#FFFFFF","i18nText":"case.in_progress"},"id":"b5fae22b-ec6b-411c-8e09-760494c2d549"},{"person":{"id":"4ce3ba24-9713-4b71-ab74-c2a3be56ee2f","initial_zh":"姜","initial_en":"","hide_name":true,"gender":"male","image_url":null,"case_person":[{"arrest_age":null,"occupation":{"type_zh":"學生","type_en":"學生"},"status":{"id":1,"type_zh":"保釋","type_en":"保釋"}},{"arrest_age":null,"occupation":{"type_zh":"學生","type_en":"學生"},"status":{"id":2,"type_zh":"還柙","type_en":"還柙"}}]},"case":{"type":"original","progress":{"id":1,"type_zh":"提堂","type_en":"提堂"}},"progress":{"id":1,"type_zh":"提堂","type_en":"提堂","fill":"#0c2c96","contrast":"#FFFFFF","i18nText":"case.in_progress"},"id":"4ce3ba24-9713-4b71-ab74-c2a3be56ee2f"},{"person":{"id":"c1178c3c-94b8-485d-afbc-c97c20ffdc9b","initial_zh":"姜","initial_en":"","hide_name":true,"gender":"male","image_url":null,"case_person":[{"arrest_age":null,"occupation":{"type_zh":"學生","type_en":"學生"},"status":{"id":1,"type_zh":"保釋","type_en":"保釋"}},{"arrest_age":null,"occupation":{"type_zh":"學生","type_en":"學生"},"status":{"id":2,"type_zh":"還柙","type_en":"還柙"}}]},"case":{"type":"original","progress":{"id":1,"type_zh":"提堂","type_en":"提堂"}},"progress":{"id":1,"type_zh":"提堂","type_en":"提堂","fill":"#0c2c96","contrast":"#FFFFFF","i18nText":"case.in_progress"},"id":"c1178c3c-94b8-485d-afbc-c97c20ffdc9b"},{"person":{"id":"57564630-4e32-45a8-89c6-bd1d9551e4df","initial_zh":"陳","initial_en":"","hide_name":true,"gender":"female","image_url":null,"case_person":[{"arrest_age":null,"occupation":{"type_zh":"學生","type_en":"學生"},"status":{"id":1,"type_zh":"保釋","type_en":"保釋"}},{"arrest_age":null,"occupation":{"type_zh":"學生","type_en":"學生"},"status":{"id":2,"type_zh":"還柙","type_en":"還柙"}}]},"case":{"type":"original","progress":{"id":1,"type_zh":"提堂","type_en":"提堂"}},"progress":{"id":1,"type_zh":"提堂","type_en":"提堂","fill":"#0c2c96","contrast":"#FFFFFF","i18nText":"case.in_progress"},"id":"57564630-4e32-45a8-89c6-bd1d9551e4df"},{"person":{"id":"d00e7869-dd5e-4963-aa92-1247d2dd78ad","initial_zh":"陳","initial_en":"","hide_name":true,"gender":"male","image_url":null,"case_person":[{"arrest_age":null,"occupation":{"type_zh":"文員","type_en":"文員"},"status":{"id":1,"type_zh":"保釋","type_en":"保釋"}},{"arrest_age":null,"occupation":{"type_zh":"文員","type_en":"文員"},"status":{"id":2,"type_zh":"還柙","type_en":"還柙"}}]},"case":{"type":"original","progress":{"id":1,"type_zh":"提堂","type_en":"提堂"}},"progress":{"id":1,"type_zh":"提堂","type_en":"提堂","fill":"#0c2c96","contrast":"#FFFFFF","i18nText":"case.in_progress"},"id":"d00e7869-dd5e-4963-aa92-1247d2dd78ad"},{"person":{"id":"42ab49e4-b666-41ff-ba13-b7eb8ef96bbc","initial_zh":"張","initial_en":"","hide_name":true,"gender":"male","image_url":null,"case_person":[{"arrest_age":null,"occupation":{"type_zh":"電競選手","type_en":""},"status":{"id":5,"type_zh":"當庭釋放","type_en":"當庭釋放"}}]},"case":{"type":"original","progress":{"id":9,"type_zh":"上訴","type_en":"上訴"}},"progress":{"id":3,"type_zh":"上訴","type_en":"上訴","fill":"#f6d973","contrast":"#000000","i18nText":"case.appeal"},"id":"42ab49e4-b666-41ff-ba13-b7eb8ef96bbc"}]}