[[[{"id":"8ad821a4-ce19-4718-b279-69cb4fc21e9a","case_num":"DCCC535/2020","type":"original","subtype":null,"next_hearing_date":"2021-08-19","close_date":null,"judge":null,"remark_zh":null,"remark_en":null,"references_zh":"【泛民15人案】\nhttps://www.hkcnews.com/event/100","references_en":null,"thisDefendant":[{"remark_zh":"","remark_en":"","references_zh":"","references_en":"","person":{"id":"56ecfc25-5a0c-404d-8916-464e9db13e48","initial_zh":"黃","initial_en":null,"hide_name":false,"gender":"male","image_url":"https://www.hkprotestdb.com/upload/images/2021-04-21/bf3616ff-225f-4327-b628-508e5e23ba84/raw.jpg","case_person":[{"arrest_age":31,"occupation":{"type_zh":"社民連主席","type_en":"社民連主席"},"status":{"id":1,"type_zh":"保釋","type_en":"保釋"}},{"arrest_age":31,"occupation":{"type_zh":"社民連主席","type_en":"社民連主席"},"status":{"id":1,"type_zh":"保釋","type_en":"保釋"}}]},"total_sentence_zh":"","total_sentence_en":"","occupation":{"type_zh":"社民連主席","type_en":"社民連主席"},"status":{"id":1,"type_zh":"保釋","type_en":"保釋"},"charges":[{"id":"5c30ae20-94ae-4a33-b0d3-2e34a59fe63b","content_zh":"於2019年10月20日，在香港組織一個未經批准的公眾遊行。","content_en":null,"charge":{"id":35,"name_zh":"組織未經批准集結","name_en":null},"sentence_sp_zh":null,"sentence_sp_en":null,"sentence":null,"sentence_2":null,"sentence_3":null,"status":null,"penalty":null,"penalty_2":null,"penalty_3":null,"arrest_location_zh":null,"arrest_location_en":null,"plead_guilty":"pending_answer","start_date":"2019-10-20","remark_zh":"","remark_en":""},{"id":"6c29fd21-2665-4c5d-8268-6c3785bbb2a3","content_zh":"於2019年10月20日，在香港明知而參與一個未經批准的公眾遊行。","content_en":null,"charge":{"id":34,"name_zh":"明知而參與未經批准集結","name_en":null},"sentence_sp_zh":null,"sentence_sp_en":null,"sentence":null,"sentence_2":null,"sentence_3":null,"status":null,"penalty":null,"penalty_2":null,"penalty_3":null,"arrest_location_zh":null,"arrest_location_en":null,"plead_guilty":"pending_answer","start_date":"2019-10-20","remark_zh":"","remark_en":""}]}],"judge_2":null,"judge_3":null,"incident":{"id":27,"date":"2019-10-20","name_zh":"10.20 九龍大遊行","name_en":"","desc_zh":"民陣發起「廢除惡法、獨立調查、重組警隊」九龍大遊行惟遭反對，有民主派人士以個人身份承接路線舉辦，至少35萬巿民參與。\n\n部分示威者在尖沙咀多處堵路及向警署投擲汽油彈，警方出動水炮車由尖沙嘴沿彌敦道噴射藍色催淚水劑，其中向尖沙嘴清真寺門外噴射藍色水，印度協會前主席Mohan Chugani、立法會議員譚文豪等遭射中。\n","desc_en":"","location":null},"progress":{"id":4,"type_zh":"審訊","type_en":"審訊"},"child_cases":[],"parent_cases":[{"id":"7ecc62d7-f7be-461b-87fc-59857466c9ae","relation_name":{"id":1,"name_zh":"轉介","name_en":"Referred"},"parent":{"id":"8f12b46e-ba7e-4d7e-b7ff-9f52b137884c","case_num":"WKCC1264/2020"}}],"case_nums":["WKCC1264/2020","DCCC535/2020"]}]],[[{"id":"77cf6373-6523-4cea-b990-b4dfd4e8de4f","case_num":"DCCC751/2020","type":"original","subtype":null,"next_hearing_date":"2021-02-26","close_date":null,"judge":null,"remark_zh":null,"remark_en":null,"references_zh":null,"references_en":null,"thisDefendant":[{"remark_zh":"","remark_en":"","references_zh":"","references_en":"","person":{"id":"3b9adeed-3e3c-4f54-a82e-041063be7183","initial_zh":"簡","initial_en":null,"hide_name":true,"gender":"male","image_url":null,"case_person":[{"arrest_age":24,"occupation":{"type_zh":"音樂教師","type_en":"音樂教師"},"status":{"id":1,"type_zh":"保釋","type_en":"保釋"}},{"arrest_age":24,"occupation":{"type_zh":"音樂教師","type_en":"音樂教師"},"status":null}]},"total_sentence_zh":"","total_sentence_en":"","occupation":{"type_zh":"音樂教師","type_en":"音樂教師"},"status":{"id":1,"type_zh":"保釋","type_en":"保釋"},"charges":[{"id":"f234c587-9e3b-4105-be2a-6a707f8b40f5","content_zh":"於2019年11月18日，在油麻地彌敦道近窩打老道交界，與其他人參與暴動。","content_en":null,"charge":{"id":6,"name_zh":"暴動","name_en":null},"sentence_sp_zh":null,"sentence_sp_en":null,"sentence":null,"sentence_2":null,"sentence_3":null,"status":null,"penalty":null,"penalty_2":null,"penalty_3":null,"arrest_location_zh":"彌敦道近窩打老道交界","arrest_location_en":null,"plead_guilty":"pending_answer","start_date":"2019-11-18","remark_zh":"","remark_en":""}]}],"judge_2":null,"judge_3":null,"incident":{"id":38,"date":"2019-11-18","name_zh":"理大圍城﹒圍魏救趙","name_en":"","desc_zh":"【11月16日至29日 — 理大圍城13天】\n\n理大被圍封、被困者多次突圍失敗後，11月18日由早至晚，家長、人群、人鏈遍佈彌敦道，史無前例近10萬人在紅磡、尖沙咀、佐敦、油麻地、旺角等地，兵分多路試圖「圍魏救趙」。\n‍\n這夜的彌敦道，場面驚險，險象橫生，在油麻地碧街更出現人踩人慘劇。\n\n單是11月18日救理大行動，逾千人被捕，被控暴動罪其中242人在11月20日提堂，為反修例運動裡，單日最多被告提堂的案件。全港7個裁判法院中，共有6個法庭要晚上開庭處理，更有案件至翌日凌晨約1時才完成提訊，打破當時法庭最晚關門時間。","desc_en":"","location":null},"progress":{"id":1,"type_zh":"提堂","type_en":"提堂"},"child_cases":[],"parent_cases":[{"id":"5fc0230e-69e4-449c-a78a-218ee5e66ea1","relation_name":{"id":1,"name_zh":"轉介","name_en":"Referred"},"parent":{"id":"fed016f3-ba17-476e-ba91-49c28228ab6e","case_num":"KCCC2790/2019"}}],"case_nums":["KCCC2790/2019","DCCC751/2020"]}]],[[{"id":"abc1e199-327f-4e14-ac46-12347754d650","case_num":"DCCC771/2020","type":"original","subtype":null,"next_hearing_date":"2023-03-27","close_date":null,"judge":null,"remark_zh":null,"remark_en":null,"references_zh":null,"references_en":null,"thisDefendant":[{"remark_zh":"","remark_en":"","references_zh":"Title\nrecord['Reference (multiple entries)']","references_en":"Title\nrecord['Reference (multiple entries)']","person":{"id":"8b70f253-e61c-4cdd-afec-4e00fd0c33b6","initial_zh":"葉","initial_en":null,"hide_name":true,"gender":"male","image_url":null,"case_person":[{"arrest_age":29,"occupation":null,"status":{"id":1,"type_zh":"保釋","type_en":"保釋"}},{"arrest_age":29,"occupation":null,"status":{"id":1,"type_zh":"保釋","type_en":"保釋"}}]},"total_sentence_zh":"","total_sentence_en":"","occupation":null,"status":{"id":1,"type_zh":"保釋","type_en":"保釋"},"charges":[{"id":"550a74f8-2f01-42f5-a611-8d8fd3c41627","content_zh":"被控於同日同地，未能向警員18094出示身分證明文件。","content_en":null,"charge":{"id":32,"name_zh":"未能出示身分證明文件","name_en":null},"sentence_sp_zh":null,"sentence_sp_en":null,"sentence":null,"sentence_2":null,"sentence_3":null,"status":null,"penalty":null,"penalty_2":null,"penalty_3":null,"arrest_location_zh":null,"arrest_location_en":null,"plead_guilty":"pending_answer","start_date":"2019-11-12","remark_zh":"","remark_en":""},{"id":"0d3991b0-a5cc-4075-bfd8-51a1e750d458","content_zh":"於2019年11月12日，在中環畢打街與德輔道中及干諾道中交界一帶，連同其他身份不詳人士參與暴動。","content_en":null,"charge":{"id":6,"name_zh":"暴動","name_en":null},"sentence_sp_zh":null,"sentence_sp_en":null,"sentence":null,"sentence_2":null,"sentence_3":null,"status":null,"penalty":null,"penalty_2":null,"penalty_3":null,"arrest_location_zh":"畢打街與德輔道中及干諾道中交界一帶","arrest_location_en":null,"plead_guilty":"pending_answer","start_date":"2019-11-12","remark_zh":"原控罪為「非法集結」，在2020年9月26日被改控暴動。","remark_en":null}]}],"judge_2":null,"judge_3":null,"incident":{"id":33,"date":"2019-11-12","name_zh":"11.12「破曉行動」","name_en":"","desc_zh":"網民發起「破曉行動」繼續大三罷。\n\n在中環午膳時間，再有「和你lunch」快閃活動，有示威者以雜物堵路，多人被捕。","desc_en":"","location":{"sub_district_zh":"中環","sub_district_en":"Central"}},"progress":{"id":4,"type_zh":"審訊","type_en":"審訊"},"child_cases":[],"parent_cases":[{"id":"56919ca2-a7ac-4b17-b380-d3390cff08e7","relation_name":{"id":1,"name_zh":"轉介","name_en":"Referred"},"parent":{"id":"9a93f54d-a0ee-4014-9534-1f99965beffa","case_num":"WKCC4273/2019"}}],"case_nums":["WKCC4273/2019","DCCC771/2020"]}]],[[{"id":"02bb3d30-b91e-4121-b0eb-ef1d47ac8bf1","case_num":"WKCC813/2021","type":"original","subtype":null,"next_hearing_date":"2021-09-23","close_date":null,"judge":{"name_zh":"蘇惠德","name_en":"SO Wai-tak","title_zh":"總裁判官","title_en":"Chief Magistrate"},"remark_zh":"控罪書顯示，案件由國家安全處高級督察張堃婷負責。","remark_en":null,"references_zh":"47人初選案\nhttps://www.hkcnews.com/event/107","references_en":null,"thisDefendant":[{"remark_zh":"","remark_en":"","references_zh":"","references_en":"","person":{"id":"bec120c2-3998-478b-9455-82e8705e7175","initial_zh":"黃","initial_en":"","hide_name":false,"gender":"female","image_url":"https://www.hkprotestdb.com/upload/images/2021-03-29/97059fe6-fa53-46ce-90b0-db5c0681bbc3/raw.jpg","case_person":[{"arrest_age":null,"occupation":{"type_zh":"無業","type_en":"無業"},"status":{"id":1,"type_zh":"保釋","type_en":"保釋"}},{"arrest_age":null,"occupation":{"type_zh":"無業","type_en":"無業"},"status":{"id":1,"type_zh":"保釋","type_en":"保釋"}}]},"total_sentence_zh":"","total_sentence_en":"","occupation":{"type_zh":"無業","type_en":"無業"},"status":{"id":1,"type_zh":"保釋","type_en":"保釋"},"charges":[{"id":"ab329660-159a-4c7a-aede-98fa59315e84","content_zh":"於2020年7月1日至2021年1月7日期間，在香港串謀及與其他人串謀，旨在顛覆國家政權，而組織、策劃、實施或參與實施，以威脅使用武力或其他非法手段。（控方列出4種「非法手段」，詳情請參閱「民主派立法會初選」的事件簡介）","content_en":"","charge":{"id":56,"name_zh":"串謀顛覆國家政權","name_en":""},"sentence_sp_zh":null,"sentence_sp_en":null,"sentence":null,"sentence_2":null,"sentence_3":null,"status":null,"penalty":null,"penalty_2":null,"penalty_3":null,"arrest_location_zh":null,"arrest_location_en":null,"plead_guilty":"pending_answer","start_date":"2020-07-01","remark_zh":"","remark_en":""}]}],"judge_2":null,"judge_3":null,"incident":{"id":65,"date":"2020-07-11","name_zh":"民主派立法會初選","name_en":"","desc_zh":"立法會選舉原定於2020年9月6日舉行，民主派就在7月11日及12日舉行「35+公民投票」初選協調，最終超過60萬人投票，但政府就以疫情為由，決定將選舉押後一年。\n\n到半年後的2021年1月6日，警方國安處以涉嫌干犯《國安法》的「顛覆國家政權罪」為由，大舉拘捕53名初選參加者及籌辦初選的人士，指他們參與初選及提出攬炒十步曲；在警署扣留調查後，全部人暫獲保釋。\n\n到3月1日，其中47人被正式起訴「串謀顛覆國家政權」，馬拉松式提堂4日後，原本有15人獲准保釋，惟律政司上訴至高等法院後，只有楊雪盈、劉偉聰、呂智恆、林景楠、黃碧雲、鄭鴻達、彭卓棋、柯耀林、何啟明、施德來及李予信可暫獲自由。\n\n＊＊＊＊＊＊＊＊＊＊＊＊\n\n控罪書指出，全部被告被控於2020年7月1日至2021年1月7日期間，在香港串謀及與其他人串謀，旨在顛覆國家政權，而組織、策劃、實施或參與實施，以威脅使用武力或其他非法手段，即：\n\n\n（一）為以下目的宣揚，進行或參與一項謀劃，旨在濫用當選立法會議員後，根據《基本法》第73條受託的職權，在立法會取得大多數控制權，藉以對香港特區政府提出的任何財政預算或公共開支，不論當中內容或內容的利弊如何，均不予區別拒絕通過；迫使香港行政長官根據《基本法》第50條解散立法會，從而癱瘓政府運作；最終導致行政長官因立法會解散和重選的立法會拒絕通過原財政預算案而根據《基本法》第52條而辭職；\n\n（二）為達致該謀劃，參選或不參選立法會選舉，及/或煽動、促使、引致、誘使他人參選或不參選該選舉；\n\n（三）承諾或同意當選立法會議員後，及/或煽動、促使、引致、誘使他人當選立法會議員後，在審核和通過政府提出的財政預算或公共開支時，按照該謀劃，行使或不行使其根據《基本法》第73條所訂的職權；\n\n（四）承諾或同意在該選舉當選後，及/或煽動、促使、引致、誘使他人在該選舉中當選後，故意或蓄意不履行，或故意或蓄意疏於履行其立法會議員職責，即擁護《基本法》，效忠香港特區，盡忠職守，遵守法律，廉潔奉公，為香港特區服務；嚴重干擾、阻撓、破壞香港特區政權機關依法履行職能的行為。","desc_en":"","location":null},"progress":{"id":1,"type_zh":"提堂","type_en":"提堂"},"child_cases":[{"id":"da62b9af-d54f-4907-b82a-6dd0b5881591","relation_name":{"id":2,"name_zh":"上訴","name_en":"Appeal"},"child":{"id":"7c2b8528-4c58-4ab0-9202-4644d573df8e","case_num":"HCCP110/2021 "}},{"id":"e07a4e80-92e4-45f4-aca0-e2303377f953","relation_name":{"id":2,"name_zh":"上訴","name_en":"Appeal"},"child":{"id":"59a5dffc-c2cb-46db-b554-3f6676e46711","case_num":"HCCP111/2021 "}},{"id":"318cabc6-9f9f-4d7d-9734-426a33f40736","relation_name":{"id":2,"name_zh":"上訴","name_en":"Appeal"},"child":{"id":"120216ca-d972-4388-9b39-5ca1cd3dca14","case_num":"HCCP112/2021 "}},{"id":"7d2afff7-aaf3-4334-a1b1-97de04bedfaa","relation_name":{"id":2,"name_zh":"上訴","name_en":"Appeal"},"child":{"id":"904b0202-7120-48a8-b532-fb65481bf21c","case_num":"HCCP113/2021 "}},{"id":"2abf8605-be06-480f-ba03-37c3690d3cf2","relation_name":{"id":2,"name_zh":"上訴","name_en":"Appeal"},"child":{"id":"e1df7258-5551-4962-964c-24ec58694215","case_num":"HCCP114/2021 "}},{"id":"aabdb770-1761-4c2e-a0a7-34249828b795","relation_name":{"id":2,"name_zh":"上訴","name_en":"Appeal"},"child":{"id":"ea10e6df-80d1-439e-888f-0c4974c91c62","case_num":"HCCP115/2021 "}},{"id":"d02364a8-8620-427d-a1cc-df8d32c31e50","relation_name":{"id":2,"name_zh":"上訴","name_en":"Appeal"},"child":{"id":"cc122bb5-823c-4c99-818e-86365c878f40","case_num":"HCCP116/2021 "}},{"id":"02a29265-929e-4390-b458-c0d8354fcc70","relation_name":{"id":2,"name_zh":"上訴","name_en":"Appeal"},"child":{"id":"2902d6bd-dcf3-4c6e-b97e-28cae0e93d67","case_num":"HCCP117/2021 "}},{"id":"f0b0e6b4-ab4c-4e14-a4fb-d1879280314b","relation_name":{"id":2,"name_zh":"上訴","name_en":"Appeal"},"child":{"id":"4b68cb77-4d08-430f-8346-4697533d8d40","case_num":"HCCP118/2021 "}},{"id":"1b3959a5-94e5-41a1-8433-6c866c727113","relation_name":{"id":2,"name_zh":"上訴","name_en":"Appeal"},"child":{"id":"2788a774-27e2-4526-b526-c95e02d21413","case_num":"HCCP119/2021 "}},{"id":"8a9ec405-7efe-47aa-ad37-4e929452307b","relation_name":{"id":2,"name_zh":"上訴","name_en":"Appeal"},"child":{"id":"61cad27d-d812-4c2a-b5a4-34ce0bea8b20","case_num":"HCCP120/2021 "}},{"id":"3dc2414b-96ce-4606-bb9f-45c55107bfc9","relation_name":{"id":2,"name_zh":"上訴","name_en":"Appeal"},"child":{"id":"4893e77e-09b1-44e6-a0f6-8c8cf66ea3aa","case_num":"HCCP126/2021"}},{"id":"9932355a-d4ce-49b8-a5ee-a1749f7f10ad","relation_name":{"id":2,"name_zh":"上訴","name_en":"Appeal"},"child":{"id":"8be24783-89d4-4ac6-9126-611ffa3dd9c2","case_num":"HCCP141/2021"}},{"id":"6a9b992e-599e-443c-be9f-92bfed07fcfd","relation_name":{"id":2,"name_zh":"上訴","name_en":"Appeal"},"child":{"id":"991fae12-c668-41f0-84f2-b1788cf33d8a","case_num":"HCCP135/2021"}},{"id":"397a9716-4147-4362-a070-d304739782ce","relation_name":{"id":2,"name_zh":"上訴","name_en":"Appeal"},"child":{"id":"f4c492aa-7aaf-45db-8f46-b00887aaaa08","case_num":"HCCP136/2021"}},{"id":"992b243c-f82f-4435-8bf7-ea4987e87c83","relation_name":{"id":2,"name_zh":"上訴","name_en":"Appeal"},"child":{"id":"19c81bfd-c484-440b-84db-f220a9df025a","case_num":"HCCP134/2021"}},{"id":"6348deb9-c0a8-47fd-aca0-117ce955c026","relation_name":{"id":2,"name_zh":"上訴","name_en":"Appeal"},"child":{"id":"6165fc2f-fad1-45b2-a889-13cfb59a5478","case_num":"HCCP137/2021"}},{"id":"8a3fc5fa-71b0-432e-9e01-aebb8da1cfc0","relation_name":{"id":2,"name_zh":"上訴","name_en":"Appeal"},"child":{"id":"dda8b1fa-42ad-4394-acc7-78589be48897","case_num":"HCCP348/2021"}},{"id":"db25472b-d20a-4e70-aeb9-368a750e7b05","relation_name":{"id":2,"name_zh":"上訴","name_en":"Appeal"},"child":{"id":"a60da10a-9ca3-4f03-a5fb-4c14897e6114","case_num":"HCCP294/2021"}}],"parent_cases":[],"case_nums":["WKCC813/2021"]},{"id":"904b0202-7120-48a8-b532-fb65481bf21c","case_num":"HCCP113/2021 ","type":"original","subtype":"bail_appeal","next_hearing_date":null,"close_date":"2021-03-11","judge":{"name_zh":"杜麗冰","name_en":"TOH","title_zh":"高等法院原訟法庭法官","title_en":"Judges of the Court of First Instance of the High Court"},"remark_zh":null,"remark_en":null,"references_zh":null,"references_en":null,"thisDefendant":[{"remark_zh":"","remark_en":"","references_zh":"","references_en":"","person":{"id":"bec120c2-3998-478b-9455-82e8705e7175","initial_zh":"黃","initial_en":"","hide_name":false,"gender":"female","image_url":"https://www.hkprotestdb.com/upload/images/2021-03-29/97059fe6-fa53-46ce-90b0-db5c0681bbc3/raw.jpg","case_person":[{"arrest_age":null,"occupation":{"type_zh":"無業","type_en":"無業"},"status":{"id":1,"type_zh":"保釋","type_en":"保釋"}},{"arrest_age":null,"occupation":{"type_zh":"無業","type_en":"無業"},"status":{"id":1,"type_zh":"保釋","type_en":"保釋"}}]},"total_sentence_zh":"","total_sentence_en":"","occupation":{"type_zh":"無業","type_en":"無業"},"status":{"id":1,"type_zh":"保釋","type_en":"保釋"},"charges":[{"id":"edcac7a0-0303-4817-87d9-1f0def596863","content_zh":"","content_en":"","charge":{"id":56,"name_zh":"串謀顛覆國家政權","name_en":""},"sentence_sp_zh":null,"sentence_sp_en":null,"sentence":null,"sentence_2":null,"sentence_3":null,"status":null,"penalty":null,"penalty_2":null,"penalty_3":null,"arrest_location_zh":"","arrest_location_en":"","plead_guilty":"pending_answer","start_date":null,"remark_zh":"律政司覆核失敗，獲准保釋","remark_en":""}]}],"judge_2":null,"judge_3":null,"incident":{"id":65,"date":"2020-07-11","name_zh":"民主派立法會初選","name_en":"","desc_zh":"立法會選舉原定於2020年9月6日舉行，民主派就在7月11日及12日舉行「35+公民投票」初選協調，最終超過60萬人投票，但政府就以疫情為由，決定將選舉押後一年。\n\n到半年後的2021年1月6日，警方國安處以涉嫌干犯《國安法》的「顛覆國家政權罪」為由，大舉拘捕53名初選參加者及籌辦初選的人士，指他們參與初選及提出攬炒十步曲；在警署扣留調查後，全部人暫獲保釋。\n\n到3月1日，其中47人被正式起訴「串謀顛覆國家政權」，馬拉松式提堂4日後，原本有15人獲准保釋，惟律政司上訴至高等法院後，只有楊雪盈、劉偉聰、呂智恆、林景楠、黃碧雲、鄭鴻達、彭卓棋、柯耀林、何啟明、施德來及李予信可暫獲自由。\n\n＊＊＊＊＊＊＊＊＊＊＊＊\n\n控罪書指出，全部被告被控於2020年7月1日至2021年1月7日期間，在香港串謀及與其他人串謀，旨在顛覆國家政權，而組織、策劃、實施或參與實施，以威脅使用武力或其他非法手段，即：\n\n\n（一）為以下目的宣揚，進行或參與一項謀劃，旨在濫用當選立法會議員後，根據《基本法》第73條受託的職權，在立法會取得大多數控制權，藉以對香港特區政府提出的任何財政預算或公共開支，不論當中內容或內容的利弊如何，均不予區別拒絕通過；迫使香港行政長官根據《基本法》第50條解散立法會，從而癱瘓政府運作；最終導致行政長官因立法會解散和重選的立法會拒絕通過原財政預算案而根據《基本法》第52條而辭職；\n\n（二）為達致該謀劃，參選或不參選立法會選舉，及/或煽動、促使、引致、誘使他人參選或不參選該選舉；\n\n（三）承諾或同意當選立法會議員後，及/或煽動、促使、引致、誘使他人當選立法會議員後，在審核和通過政府提出的財政預算或公共開支時，按照該謀劃，行使或不行使其根據《基本法》第73條所訂的職權；\n\n（四）承諾或同意在該選舉當選後，及/或煽動、促使、引致、誘使他人在該選舉中當選後，故意或蓄意不履行，或故意或蓄意疏於履行其立法會議員職責，即擁護《基本法》，效忠香港特區，盡忠職守，遵守法律，廉潔奉公，為香港特區服務；嚴重干擾、阻撓、破壞香港特區政權機關依法履行職能的行為。","desc_en":"","location":null},"progress":{"id":1,"type_zh":"提堂","type_en":"提堂"},"child_cases":[],"parent_cases":[{"id":"7d2afff7-aaf3-4334-a1b1-97de04bedfaa","relation_name":{"id":2,"name_zh":"上訴","name_en":"Appeal"},"parent":{"id":"02bb3d30-b91e-4121-b0eb-ef1d47ac8bf1","case_num":"WKCC813/2021"}}],"case_nums":["HCCP113/2021 "]}]],[[{"id":"5a583485-0c02-49e9-b887-f4c3794462c8","case_num":"DCCC799/2020","type":"original","subtype":null,"next_hearing_date":"2022-11-07","close_date":null,"judge":null,"remark_zh":null,"remark_en":null,"references_zh":null,"references_en":null,"thisDefendant":[{"remark_zh":"","remark_en":"","references_zh":"","references_en":"","person":{"id":"6267276f-5a41-4cd0-85c9-b64225065652","initial_zh":"*","initial_en":"","hide_name":true,"gender":"female","image_url":null,"case_person":[{"arrest_age":null,"occupation":{"type_zh":"學生","type_en":"學生"},"status":{"id":1,"type_zh":"保釋","type_en":"保釋"}}]},"total_sentence_zh":"","total_sentence_en":"","occupation":{"type_zh":"學生","type_en":"學生"},"status":{"id":1,"type_zh":"保釋","type_en":"保釋"},"charges":[{"id":"9436d7ef-6028-4a05-be68-5e07b508263f","content_zh":"於2019年11月18日，在油麻地彌敦道近窩打老道交界，連同其他人參與暴動。","content_en":"","charge":{"id":6,"name_zh":"暴動","name_en":null},"sentence_sp_zh":null,"sentence_sp_en":null,"sentence":null,"sentence_2":null,"sentence_3":null,"status":null,"penalty":null,"penalty_2":null,"penalty_3":null,"arrest_location_zh":"彌敦道近窩打老道交界","arrest_location_en":"","plead_guilty":"pending_answer","start_date":"2019-11-18","remark_zh":"","remark_en":""}]}],"judge_2":null,"judge_3":null,"incident":{"id":38,"date":"2019-11-18","name_zh":"理大圍城﹒圍魏救趙","name_en":"","desc_zh":"【11月16日至29日 — 理大圍城13天】\n\n理大被圍封、被困者多次突圍失敗後，11月18日由早至晚，家長、人群、人鏈遍佈彌敦道，史無前例近10萬人在紅磡、尖沙咀、佐敦、油麻地、旺角等地，兵分多路試圖「圍魏救趙」。\n‍\n這夜的彌敦道，場面驚險，險象橫生，在油麻地碧街更出現人踩人慘劇。\n\n單是11月18日救理大行動，逾千人被捕，被控暴動罪其中242人在11月20日提堂，為反修例運動裡，單日最多被告提堂的案件。全港7個裁判法院中，共有6個法庭要晚上開庭處理，更有案件至翌日凌晨約1時才完成提訊，打破當時法庭最晚關門時間。","desc_en":"","location":null},"progress":{"id":4,"type_zh":"審訊","type_en":"審訊"},"child_cases":[],"parent_cases":[],"case_nums":["DCCC799/2020"]}]],[[{"id":"0a1916dc-8514-4838-abff-d76cfb444602","case_num":"DCCC820/2019","type":"original","subtype":null,"next_hearing_date":null,"close_date":null,"judge":null,"remark_zh":null,"remark_en":null,"references_zh":"【7.28上環暴動案】\nhttps://www.hkcnews.com/event/98","references_en":null,"thisDefendant":[{"remark_zh":"","remark_en":"","references_zh":"Title\nrecord['Reference (multiple entries)']","references_en":"Title\nrecord['Reference (multiple entries)']","person":{"id":"b6a939ac-86d8-4c16-bdc3-f15d006f9e5c","initial_zh":"廖","initial_en":null,"hide_name":true,"gender":"female","image_url":null,"case_person":[{"arrest_age":19,"occupation":{"type_zh":"學生","type_en":"學生"},"status":{"id":1,"type_zh":"保釋","type_en":"保釋"}},{"arrest_age":19,"occupation":{"type_zh":"學生","type_en":"學生"},"status":{"id":1,"type_zh":"保釋","type_en":"保釋"}},{"arrest_age":19,"occupation":{"type_zh":"學生","type_en":"學生"},"status":{"id":1,"type_zh":"保釋","type_en":"保釋"}}]},"total_sentence_zh":"","total_sentence_en":"","occupation":{"type_zh":"學生","type_en":"學生"},"status":{"id":1,"type_zh":"保釋","type_en":"保釋"},"charges":[{"id":"ef702deb-29ea-4db4-87b8-c63ae0193976","content_zh":"於2019年7月28日，在香港上環幹諾道中及文華里附近，連同其他人參與暴動。","content_en":null,"charge":{"id":6,"name_zh":"暴動","name_en":null},"sentence_sp_zh":null,"sentence_sp_en":null,"sentence":null,"sentence_2":null,"sentence_3":null,"status":null,"penalty":null,"penalty_2":null,"penalty_3":null,"arrest_location_zh":"干諾道西及文華里交界","arrest_location_en":null,"plead_guilty":"pending_answer","start_date":"2019-07-28","remark_zh":"","remark_en":""}]}],"judge_2":null,"judge_3":null,"incident":{"id":8,"date":"2019-07-28","name_zh":"7.28 上環衝突","name_en":"","desc_zh":"網民發起在中環遮打花園集會，主題為追究警方在7.21上環清場時，無預警下對示威者開槍（橡膠子彈）、抗議7.21元朗白衣人無差別襲擊。集會開始不久，示威者在上環、金鐘、灣仔等地方聚集，入夜後發生激烈警民衝突。\n\n警方當晚頻密發射催淚彈，多次在地面及高位開槍，共使用408枚催淚彈、95發橡膠子彈、50發海綿彈及2枚布袋彈。\n\n這天49人被捕，其中44人被控暴動罪，也是警方在運動中首次大規模控以暴動。\n","desc_en":"","location":{"sub_district_zh":"上環","sub_district_en":"Sheung Wan"}},"progress":{"id":4,"type_zh":"審訊","type_en":"審訊"},"child_cases":[],"parent_cases":[{"id":"f6192d2b-ac71-4e2d-92b4-7ec60a4c6ecd","relation_name":{"id":1,"name_zh":"轉介","name_en":"Referred"},"parent":{"id":"9ade0c26-5daf-4eb7-ae39-601c1825136e","case_num":"WKCC3439/2019"}}],"case_nums":["ESCC1845/2019","WKCC3439/2019","DCCC820/2019"]}]],[[{"id":"50e93368-8238-45d6-bc13-6382f0e301ab","case_num":"DCCC668/2020","type":"original","subtype":null,"next_hearing_date":"2022-01-03","close_date":null,"judge":null,"remark_zh":null,"remark_en":null,"references_zh":null,"references_en":null,"thisDefendant":[{"remark_zh":"首提堂在裁判法院被拒保䆁，及後在高等法院獲准保釋。","remark_en":"","references_zh":"","references_en":"","person":{"id":"4bcf408b-4a92-4a75-99a6-71b898c79e9d","initial_zh":"馬","initial_en":"","hide_name":true,"gender":"male","image_url":null,"case_person":[{"arrest_age":null,"occupation":{"type_zh":"學生","type_en":"學生"},"status":{"id":1,"type_zh":"保釋","type_en":"保釋"}},{"arrest_age":null,"occupation":{"type_zh":"學生","type_en":"學生"},"status":{"id":1,"type_zh":"保釋","type_en":"保釋"}},{"arrest_age":null,"occupation":{"type_zh":"學生","type_en":"學生"},"status":{"id":1,"type_zh":"保釋","type_en":"保釋"}}]},"total_sentence_zh":"","total_sentence_en":"","occupation":{"type_zh":"學生","type_en":"學生"},"status":{"id":1,"type_zh":"保釋","type_en":"保釋"},"charges":[{"id":"86c43503-f5e6-470c-ab93-fb477696f2c9","content_zh":"於2020年1月27日凌晨，在旺角山東街與砵蘭街交界，與其他不知名者串謀非法及惡意傷害男子X。","content_en":"","charge":{"id":12,"name_zh":"串謀有意圖傷人","name_en":null},"sentence_sp_zh":null,"sentence_sp_en":null,"sentence":null,"sentence_2":null,"sentence_3":null,"status":null,"penalty":null,"penalty_2":null,"penalty_3":null,"arrest_location_zh":"山東街與砵蘭街交界","arrest_location_en":null,"plead_guilty":"pending_answer","start_date":"2020-01-27","remark_zh":"","remark_en":""},{"id":"908c18e9-f0d4-4471-8b8e-bb5ff58a46dc","content_zh":"於2020年1月27日，在旺角山東街與砵蘭街交界，與其他身份不詳的人參與暴動。","content_en":"","charge":{"id":6,"name_zh":"暴動","name_en":null},"sentence_sp_zh":null,"sentence_sp_en":null,"sentence":null,"sentence_2":null,"sentence_3":null,"status":null,"penalty":null,"penalty_2":null,"penalty_3":null,"arrest_location_zh":"山東街與砵蘭街交界","arrest_location_en":null,"plead_guilty":"pending_answer","start_date":"2020-01-27","remark_zh":"","remark_en":""},{"id":"ad1ee1d3-c65e-4760-a445-ba9460121ff1","content_zh":"於2020年1月27日，在旺角山東街與砵蘭街交界，與其他身份不詳的人非法囚禁男子X，對他造成不利，並違反其意願而將其禁錮。","content_en":"","charge":{"id":13,"name_zh":"非法禁錮","name_en":null},"sentence_sp_zh":null,"sentence_sp_en":null,"sentence":null,"sentence_2":null,"sentence_3":null,"status":null,"penalty":null,"penalty_2":null,"penalty_3":null,"arrest_location_zh":"山東街與砵蘭街交界","arrest_location_en":null,"plead_guilty":"pending_answer","start_date":"2020-01-27","remark_zh":"","remark_en":""}]}],"judge_2":null,"judge_3":null,"incident":{"id":62,"date":"2020-01-26","name_zh":"1.26 年初二旺角衝突四周年","name_en":"","desc_zh":"有本土組織在農曆年初二發起「勿忘魚蛋、捍衛本土」集會，紀念2016年旺角衝突四周年，遭警方發出禁止公眾集會通知書。惟旺角街頭仍有大批市民聚集，事件期後再度演變為警民衝突，警方發射催淚彈驅散。","desc_en":"","location":{"sub_district_zh":"旺角","sub_district_en":"Mong Kok"}},"progress":{"id":4,"type_zh":"審訊","type_en":"審訊"},"child_cases":[],"parent_cases":[{"id":"579843c0-bbb3-4e18-8cf8-a4ccb23350d3","relation_name":{"id":1,"name_zh":"轉介","name_en":"Referred"},"parent":{"id":"68a2bc24-f097-486e-a535-757328ee3e16","case_num":"KCCC240/2020"}}],"case_nums":["WKCC323/2020","KCCC240/2020","DCCC668/2020"]}]],[[{"id":"c379b19f-21ff-4973-aeaf-2e2b8331ec56","case_num":"DCCC240/2021","type":"original","subtype":null,"next_hearing_date":"2022-10-17","close_date":null,"judge":null,"remark_zh":null,"remark_en":null,"references_zh":null,"references_en":null,"thisDefendant":[{"remark_zh":"","remark_en":"","references_zh":"","references_en":"","person":{"id":"e14298f8-6758-495a-a227-7bdeff71da0e","initial_zh":"馮","initial_en":null,"hide_name":true,"gender":"female","image_url":null,"case_person":[{"arrest_age":39,"occupation":{"type_zh":"電腦技術員","type_en":"電腦技術員"},"status":{"id":1,"type_zh":"保釋","type_en":"保釋"}},{"arrest_age":39,"occupation":{"type_zh":"電腦技術員","type_en":"電腦技術員"},"status":{"id":1,"type_zh":"保釋","type_en":"保釋"}},{"arrest_age":39,"occupation":{"type_zh":"電腦技術員","type_en":"電腦技術員"},"status":null}]},"total_sentence_zh":"","total_sentence_en":"","occupation":{"type_zh":"電腦技術員","type_en":"電腦技術員"},"status":{"id":1,"type_zh":"保釋","type_en":"保釋"},"charges":[{"id":"c8dc5455-0899-47f7-abee-410b68ce97a5","content_zh":"於2019年9月29日，在金鐘夏愨道政府總部外一帶連同其他不知名人士參與暴動。","content_en":null,"charge":{"id":6,"name_zh":"暴動","name_en":null},"sentence_sp_zh":null,"sentence_sp_en":null,"sentence":null,"sentence_2":null,"sentence_3":null,"status":null,"penalty":null,"penalty_2":null,"penalty_3":null,"arrest_location_zh":"政府總部外","arrest_location_en":null,"plead_guilty":"pending_answer","start_date":"2019-09-29","remark_zh":null,"remark_en":null}]}],"judge_2":null,"judge_3":null,"incident":{"id":20,"date":"2019-09-29","name_zh":"9.29 全球反極權大遊行","name_en":"","desc_zh":"網民發起下午在港島區舉行「全球反極權大遊行」，警方及示威者在金鐘、灣仔一帶爆發衝突。全日共146人被捕，其中96人被控暴動罪。\n\n同日，印尼女記者Veby Mega Indah懷疑被警方發射的布袋彈擊中右眼失明。","desc_en":"","location":{"sub_district_zh":"金鐘","sub_district_en":"Admiralty"}},"progress":{"id":4,"type_zh":"審訊","type_en":"審訊"},"child_cases":[],"parent_cases":[{"id":"f31ed210-2591-4741-8015-c6d7b062e524","relation_name":{"id":1,"name_zh":"轉介","name_en":"Referred"},"parent":{"id":"b6117084-1409-46c9-888d-4e717f7d4c80","case_num":"DCCC293/2020"}}],"case_nums":["WKCC3791/2019","DCCC293/2020","DCCC240/2021"]}]],[[{"id":"9ade0c26-5daf-4eb7-ae39-601c1825136e","case_num":"WKCC3439/2019","type":"original","subtype":null,"next_hearing_date":"2021-06-07","close_date":null,"judge":null,"remark_zh":null,"remark_en":null,"references_zh":null,"references_en":null,"thisDefendant":[{"remark_zh":"","remark_en":"","references_zh":"Title\nrecord['Reference (multiple entries)']","references_en":"Title\nrecord['Reference (multiple entries)']","person":{"id":"5cc428a1-ad5b-4937-bb7d-668100d6fc54","initial_zh":"廖","initial_en":null,"hide_name":true,"gender":"male","image_url":null,"case_person":[{"arrest_age":28,"occupation":{"type_zh":"文員","type_en":"文員"},"status":{"id":4,"type_zh":"法庭批出拘捕令","type_en":"法庭批出拘捕令"}},{"arrest_age":28,"occupation":{"type_zh":"文員","type_en":"文員"},"status":{"id":4,"type_zh":"法庭批出拘捕令","type_en":"法庭批出拘捕令"}}]},"total_sentence_zh":"","total_sentence_en":"","occupation":{"type_zh":"文員","type_en":"文員"},"status":{"id":4,"type_zh":"法庭批出拘捕令","type_en":"法庭批出拘捕令"},"charges":[{"id":"16d2ac37-d468-4a63-9d2c-6e7c5505e5ca","content_zh":"於2019年7月28日，在香港上環幹諾道中及文華里附近，連同其他人參與暴動。","content_en":null,"charge":{"id":6,"name_zh":"暴動","name_en":null},"sentence_sp_zh":null,"sentence_sp_en":null,"sentence":null,"sentence_2":null,"sentence_3":null,"status":null,"penalty":null,"penalty_2":null,"penalty_3":null,"arrest_location_zh":"干諾道西及文華里交界","arrest_location_en":null,"plead_guilty":"pending_answer","start_date":"2019-07-28","remark_zh":"","remark_en":""}]}],"judge_2":null,"judge_3":null,"incident":{"id":8,"date":"2019-07-28","name_zh":"7.28 上環衝突","name_en":"","desc_zh":"網民發起在中環遮打花園集會，主題為追究警方在7.21上環清場時，無預警下對示威者開槍（橡膠子彈）、抗議7.21元朗白衣人無差別襲擊。集會開始不久，示威者在上環、金鐘、灣仔等地方聚集，入夜後發生激烈警民衝突。\n\n警方當晚頻密發射催淚彈，多次在地面及高位開槍，共使用408枚催淚彈、95發橡膠子彈、50發海綿彈及2枚布袋彈。\n\n這天49人被捕，其中44人被控暴動罪，也是警方在運動中首次大規模控以暴動。\n","desc_en":"","location":{"sub_district_zh":"上環","sub_district_en":"Sheung Wan"}},"progress":{"id":4,"type_zh":"審訊","type_en":"審訊"},"child_cases":[{"id":"f6192d2b-ac71-4e2d-92b4-7ec60a4c6ecd","relation_name":{"id":1,"name_zh":"轉介","name_en":"Referred"},"child":{"id":"0a1916dc-8514-4838-abff-d76cfb444602","case_num":"DCCC820/2019"}}],"parent_cases":[{"id":"394cb250-441e-4802-8d53-51207bff35b4","relation_name":{"id":1,"name_zh":"轉介","name_en":"Referred"},"parent":{"id":"5e545e08-b723-44f4-bbb3-a665e302052e","case_num":"ESCC1845/2019"}}],"case_nums":["ESCC1845/2019","WKCC3439/2019"]}]],[[{"id":"f0c9a7be-b3eb-489a-a2f6-125b5193cb85","case_num":"DCCC9/2020","type":"original","subtype":null,"next_hearing_date":null,"close_date":"2021-01-18","judge":null,"remark_zh":"律政司正就罪名不成立的被告作定罪上訴","remark_en":null,"references_zh":"裁決理由書\nhttps://legalref.judiciary.hk/lrs/common/search/search_result_detail_frame.jsp?DIS=132618&QS=%28DCCC%7C9%2F2020%29&TP=RV\n判刑理由書\nhttps://legalref.judiciary.hk/lrs/common/search/search_result_detail_frame.jsp?DIS=133177&QS=%28DCCC%7C9%2F2020%29&TP=RS","references_en":null,"thisDefendant":[{"remark_zh":"","remark_en":"","references_zh":"","references_en":"","person":{"id":"cffaf272-d1dd-482e-bbe9-57d217d1b036","initial_zh":"陳","initial_en":null,"hide_name":true,"gender":"male","image_url":null,"case_person":[{"arrest_age":39,"occupation":{"type_zh":"裝修工人","type_en":"裝修工人"},"status":{"id":5,"type_zh":"當庭釋放","type_en":"當庭釋放"}},{"arrest_age":39,"occupation":{"type_zh":"裝修工人","type_en":"裝修工人"},"status":{"id":5,"type_zh":"當庭釋放","type_en":"當庭釋放"}}]},"total_sentence_zh":"","total_sentence_en":"","occupation":{"type_zh":"裝修工人","type_en":"裝修工人"},"status":{"id":5,"type_zh":"當庭釋放","type_en":"當庭釋放"},"charges":[{"id":"aa1ee2d5-080d-4d8f-aa07-26803360a8bb","content_zh":"於2019年8月31日，在記利佐治街1號一帶（原控罪地點為銅鑼灣百德新街一帶），連同其他人參與暴動。","content_en":null,"charge":{"id":6,"name_zh":"暴動","name_en":null},"sentence_sp_zh":null,"sentence_sp_en":null,"sentence":null,"sentence_2":null,"sentence_3":null,"status":{"id":2,"type_zh":"罪名不成立","type_en":"罪名不成立"},"penalty":null,"penalty_2":null,"penalty_3":null,"arrest_location_zh":"記利佐治街1號一帶","arrest_location_en":null,"plead_guilty":"plead_no_guilty","start_date":"2019-08-31","remark_zh":"因留醫曾缺席2019年9月2日的首聆訊。","remark_en":null}]}],"judge_2":null,"judge_3":null,"incident":{"id":16,"date":"2019-08-31","name_zh":"8.31港島「自由行」","name_en":"","desc_zh":"民陣原定在「人大8.31落閘」5周年發起遊行及集會，惟遭警方反對，大批市民仍自發到港島上街「自由行」、宗教遊行等活動，事件演變成警民衝突。\n\n晚上，約百名警察衝入港鐵太子站月台及車廂，無差別施放胡椒噴劑及揮棍棒打市民，多人受傷及被制服，事後亦流傳站內有人命傷亡。","desc_en":"","location":null},"progress":{"id":9,"type_zh":"上訴","type_en":"上訴"},"child_cases":[],"parent_cases":[{"id":"ade2e0cb-710d-4b8a-a9c4-36dc78aefaba","relation_name":{"id":1,"name_zh":"轉介","name_en":"Referred"},"parent":{"id":"f5ee9261-591c-4f81-8370-2f7410c803da","case_num":"WKCC3533/2019"}},{"id":"dd18df17-63df-40a2-a1f2-3fcc9b1f6dfb","relation_name":{"id":1,"name_zh":"轉介","name_en":"Referred"},"parent":{"id":"22cd1ab9-784e-44eb-bb54-57b2775f81e0","case_num":"WKCC3532/2019"}}],"case_nums":["WKCC3533/2019","DCCC9/2020"]}]],[[{"id":"9bc3a0a4-9caa-4894-964f-6ef85a154a25","case_num":"DCCC789/2020","type":"original","subtype":null,"next_hearing_date":null,"close_date":null,"judge":null,"remark_zh":null,"remark_en":null,"references_zh":null,"references_en":null,"thisDefendant":[{"remark_zh":"","remark_en":"","references_zh":"","references_en":"","person":{"id":"ea61ae61-b0fb-491d-b261-76ece2a0e610","initial_zh":"潘","initial_en":null,"hide_name":true,"gender":"male","image_url":null,"case_person":[{"arrest_age":22,"occupation":{"type_zh":"設計師","type_en":"設計師"},"status":{"id":1,"type_zh":"保釋","type_en":"保釋"}},{"arrest_age":22,"occupation":{"type_zh":"設計師","type_en":"設計師"},"status":{"id":1,"type_zh":"保釋","type_en":"保釋"}}]},"total_sentence_zh":"","total_sentence_en":"","occupation":{"type_zh":"設計師","type_en":"設計師"},"status":{"id":1,"type_zh":"保釋","type_en":"保釋"},"charges":[{"id":"183c52a0-2dd1-4014-84fe-bfb2a00654aa","content_zh":"於2019年11月18日，在油麻地彌敦道近窩打老道交界，與其他人參與暴動。","content_en":null,"charge":{"id":6,"name_zh":"暴動","name_en":null},"sentence_sp_zh":null,"sentence_sp_en":null,"sentence":null,"sentence_2":null,"sentence_3":null,"status":null,"penalty":null,"penalty_2":null,"penalty_3":null,"arrest_location_zh":"彌敦道近窩打老道交界","arrest_location_en":null,"plead_guilty":"pending_answer","start_date":"2019-11-18","remark_zh":"","remark_en":""}]}],"judge_2":null,"judge_3":null,"incident":{"id":38,"date":"2019-11-18","name_zh":"理大圍城﹒圍魏救趙","name_en":"","desc_zh":"【11月16日至29日 — 理大圍城13天】\n\n理大被圍封、被困者多次突圍失敗後，11月18日由早至晚，家長、人群、人鏈遍佈彌敦道，史無前例近10萬人在紅磡、尖沙咀、佐敦、油麻地、旺角等地，兵分多路試圖「圍魏救趙」。\n‍\n這夜的彌敦道，場面驚險，險象橫生，在油麻地碧街更出現人踩人慘劇。\n\n單是11月18日救理大行動，逾千人被捕，被控暴動罪其中242人在11月20日提堂，為反修例運動裡，單日最多被告提堂的案件。全港7個裁判法院中，共有6個法庭要晚上開庭處理，更有案件至翌日凌晨約1時才完成提訊，打破當時法庭最晚關門時間。","desc_en":"","location":null},"progress":{"id":1,"type_zh":"提堂","type_en":"提堂"},"child_cases":[],"parent_cases":[{"id":"eedf1926-64ad-4b56-8f73-b66c395efd8f","relation_name":{"id":1,"name_zh":"轉介","name_en":"Referred"},"parent":{"id":"985ad635-7842-405f-88e9-47afe9adc207","case_num":"KCCC2788/2019"}}],"case_nums":["KCCC2788/2019","DCCC789/2020"]}]],[[{"id":"02bb3d30-b91e-4121-b0eb-ef1d47ac8bf1","case_num":"WKCC813/2021","type":"original","subtype":null,"next_hearing_date":"2021-09-23","close_date":null,"judge":{"name_zh":"蘇惠德","name_en":"SO Wai-tak","title_zh":"總裁判官","title_en":"Chief Magistrate"},"remark_zh":"控罪書顯示，案件由國家安全處高級督察張堃婷負責。","remark_en":null,"references_zh":"47人初選案\nhttps://www.hkcnews.com/event/107","references_en":null,"thisDefendant":[{"remark_zh":null,"remark_en":"","references_zh":"","references_en":"","person":{"id":"0c902799-bdb9-4102-84d6-5490e7f48556","initial_zh":"戴","initial_en":"","hide_name":false,"gender":"male","image_url":"https://www.hkprotestdb.com/upload/images/2021-04-21/9698c517-6a7e-4db4-bc5d-4ec0b852e696/raw.jpg","case_person":[{"arrest_age":null,"occupation":{"type_zh":"退休人士","type_en":""},"status":{"id":3,"type_zh":"服刑中","type_en":"服刑中"}}]},"total_sentence_zh":"","total_sentence_en":"","occupation":{"type_zh":"退休人士","type_en":""},"status":{"id":3,"type_zh":"服刑中","type_en":"服刑中"},"charges":[{"id":"8f386e82-1636-42fb-89ce-0b793952ff58","content_zh":"於2020年7月1日至2021年1月7日期間，在香港串謀及與其他人串謀，旨在顛覆國家政權，而組織、策劃、實施或參與實施，以威脅使用武力或其他非法手段。（控方列出4種「非法手段」，詳情請參閱「民主派立法會初選」的事件簡介）","content_en":"","charge":{"id":56,"name_zh":"串謀顛覆國家政權","name_en":""},"sentence_sp_zh":null,"sentence_sp_en":null,"sentence":null,"sentence_2":null,"sentence_3":null,"status":null,"penalty":null,"penalty_2":null,"penalty_3":null,"arrest_location_zh":null,"arrest_location_en":null,"plead_guilty":"pending_answer","start_date":"2020-07-01","remark_zh":"因民主派初選案被還柙；另因2019年佔中案正在服刑。","remark_en":""}]}],"judge_2":null,"judge_3":null,"incident":{"id":65,"date":"2020-07-11","name_zh":"民主派立法會初選","name_en":"","desc_zh":"立法會選舉原定於2020年9月6日舉行，民主派就在7月11日及12日舉行「35+公民投票」初選協調，最終超過60萬人投票，但政府就以疫情為由，決定將選舉押後一年。\n\n到半年後的2021年1月6日，警方國安處以涉嫌干犯《國安法》的「顛覆國家政權罪」為由，大舉拘捕53名初選參加者及籌辦初選的人士，指他們參與初選及提出攬炒十步曲；在警署扣留調查後，全部人暫獲保釋。\n\n到3月1日，其中47人被正式起訴「串謀顛覆國家政權」，馬拉松式提堂4日後，原本有15人獲准保釋，惟律政司上訴至高等法院後，只有楊雪盈、劉偉聰、呂智恆、林景楠、黃碧雲、鄭鴻達、彭卓棋、柯耀林、何啟明、施德來及李予信可暫獲自由。\n\n＊＊＊＊＊＊＊＊＊＊＊＊\n\n控罪書指出，全部被告被控於2020年7月1日至2021年1月7日期間，在香港串謀及與其他人串謀，旨在顛覆國家政權，而組織、策劃、實施或參與實施，以威脅使用武力或其他非法手段，即：\n\n\n（一）為以下目的宣揚，進行或參與一項謀劃，旨在濫用當選立法會議員後，根據《基本法》第73條受託的職權，在立法會取得大多數控制權，藉以對香港特區政府提出的任何財政預算或公共開支，不論當中內容或內容的利弊如何，均不予區別拒絕通過；迫使香港行政長官根據《基本法》第50條解散立法會，從而癱瘓政府運作；最終導致行政長官因立法會解散和重選的立法會拒絕通過原財政預算案而根據《基本法》第52條而辭職；\n\n（二）為達致該謀劃，參選或不參選立法會選舉，及/或煽動、促使、引致、誘使他人參選或不參選該選舉；\n\n（三）承諾或同意當選立法會議員後，及/或煽動、促使、引致、誘使他人當選立法會議員後，在審核和通過政府提出的財政預算或公共開支時，按照該謀劃，行使或不行使其根據《基本法》第73條所訂的職權；\n\n（四）承諾或同意在該選舉當選後，及/或煽動、促使、引致、誘使他人在該選舉中當選後，故意或蓄意不履行，或故意或蓄意疏於履行其立法會議員職責，即擁護《基本法》，效忠香港特區，盡忠職守，遵守法律，廉潔奉公，為香港特區服務；嚴重干擾、阻撓、破壞香港特區政權機關依法履行職能的行為。","desc_en":"","location":null},"progress":{"id":1,"type_zh":"提堂","type_en":"提堂"},"child_cases":[{"id":"da62b9af-d54f-4907-b82a-6dd0b5881591","relation_name":{"id":2,"name_zh":"上訴","name_en":"Appeal"},"child":{"id":"7c2b8528-4c58-4ab0-9202-4644d573df8e","case_num":"HCCP110/2021 "}},{"id":"e07a4e80-92e4-45f4-aca0-e2303377f953","relation_name":{"id":2,"name_zh":"上訴","name_en":"Appeal"},"child":{"id":"59a5dffc-c2cb-46db-b554-3f6676e46711","case_num":"HCCP111/2021 "}},{"id":"318cabc6-9f9f-4d7d-9734-426a33f40736","relation_name":{"id":2,"name_zh":"上訴","name_en":"Appeal"},"child":{"id":"120216ca-d972-4388-9b39-5ca1cd3dca14","case_num":"HCCP112/2021 "}},{"id":"7d2afff7-aaf3-4334-a1b1-97de04bedfaa","relation_name":{"id":2,"name_zh":"上訴","name_en":"Appeal"},"child":{"id":"904b0202-7120-48a8-b532-fb65481bf21c","case_num":"HCCP113/2021 "}},{"id":"2abf8605-be06-480f-ba03-37c3690d3cf2","relation_name":{"id":2,"name_zh":"上訴","name_en":"Appeal"},"child":{"id":"e1df7258-5551-4962-964c-24ec58694215","case_num":"HCCP114/2021 "}},{"id":"aabdb770-1761-4c2e-a0a7-34249828b795","relation_name":{"id":2,"name_zh":"上訴","name_en":"Appeal"},"child":{"id":"ea10e6df-80d1-439e-888f-0c4974c91c62","case_num":"HCCP115/2021 "}},{"id":"d02364a8-8620-427d-a1cc-df8d32c31e50","relation_name":{"id":2,"name_zh":"上訴","name_en":"Appeal"},"child":{"id":"cc122bb5-823c-4c99-818e-86365c878f40","case_num":"HCCP116/2021 "}},{"id":"02a29265-929e-4390-b458-c0d8354fcc70","relation_name":{"id":2,"name_zh":"上訴","name_en":"Appeal"},"child":{"id":"2902d6bd-dcf3-4c6e-b97e-28cae0e93d67","case_num":"HCCP117/2021 "}},{"id":"f0b0e6b4-ab4c-4e14-a4fb-d1879280314b","relation_name":{"id":2,"name_zh":"上訴","name_en":"Appeal"},"child":{"id":"4b68cb77-4d08-430f-8346-4697533d8d40","case_num":"HCCP118/2021 "}},{"id":"1b3959a5-94e5-41a1-8433-6c866c727113","relation_name":{"id":2,"name_zh":"上訴","name_en":"Appeal"},"child":{"id":"2788a774-27e2-4526-b526-c95e02d21413","case_num":"HCCP119/2021 "}},{"id":"8a9ec405-7efe-47aa-ad37-4e929452307b","relation_name":{"id":2,"name_zh":"上訴","name_en":"Appeal"},"child":{"id":"61cad27d-d812-4c2a-b5a4-34ce0bea8b20","case_num":"HCCP120/2021 "}},{"id":"3dc2414b-96ce-4606-bb9f-45c55107bfc9","relation_name":{"id":2,"name_zh":"上訴","name_en":"Appeal"},"child":{"id":"4893e77e-09b1-44e6-a0f6-8c8cf66ea3aa","case_num":"HCCP126/2021"}},{"id":"9932355a-d4ce-49b8-a5ee-a1749f7f10ad","relation_name":{"id":2,"name_zh":"上訴","name_en":"Appeal"},"child":{"id":"8be24783-89d4-4ac6-9126-611ffa3dd9c2","case_num":"HCCP141/2021"}},{"id":"6a9b992e-599e-443c-be9f-92bfed07fcfd","relation_name":{"id":2,"name_zh":"上訴","name_en":"Appeal"},"child":{"id":"991fae12-c668-41f0-84f2-b1788cf33d8a","case_num":"HCCP135/2021"}},{"id":"397a9716-4147-4362-a070-d304739782ce","relation_name":{"id":2,"name_zh":"上訴","name_en":"Appeal"},"child":{"id":"f4c492aa-7aaf-45db-8f46-b00887aaaa08","case_num":"HCCP136/2021"}},{"id":"992b243c-f82f-4435-8bf7-ea4987e87c83","relation_name":{"id":2,"name_zh":"上訴","name_en":"Appeal"},"child":{"id":"19c81bfd-c484-440b-84db-f220a9df025a","case_num":"HCCP134/2021"}},{"id":"6348deb9-c0a8-47fd-aca0-117ce955c026","relation_name":{"id":2,"name_zh":"上訴","name_en":"Appeal"},"child":{"id":"6165fc2f-fad1-45b2-a889-13cfb59a5478","case_num":"HCCP137/2021"}},{"id":"8a3fc5fa-71b0-432e-9e01-aebb8da1cfc0","relation_name":{"id":2,"name_zh":"上訴","name_en":"Appeal"},"child":{"id":"dda8b1fa-42ad-4394-acc7-78589be48897","case_num":"HCCP348/2021"}},{"id":"db25472b-d20a-4e70-aeb9-368a750e7b05","relation_name":{"id":2,"name_zh":"上訴","name_en":"Appeal"},"child":{"id":"a60da10a-9ca3-4f03-a5fb-4c14897e6114","case_num":"HCCP294/2021"}}],"parent_cases":[],"case_nums":["WKCC813/2021"]}]],[[{"id":"c21241be-d81f-42f5-82cb-7f0feedc1ed2","case_num":"DCCC872/2019","type":"original","subtype":null,"next_hearing_date":null,"close_date":"2020-07-24","judge":{"name_zh":"郭啟安","name_en":"Anthony KWOK","title_zh":"區域法院法官","title_en":"District Judges"},"remark_zh":null,"remark_en":null,"references_zh":"【7.28上環暴動案】\nhttps://www.hkcnews.com/event/98\n裁決理由書\nhttps://legalref.judiciary.hk/lrs/common/search/search_result_detail_frame.jsp?DIS=129617&QS=%28DCCC%7C872%2F2019%29&TP=RV\n判刑理由書\nhttps://legalref.judiciary.hk/lrs/common/ju/ju_frame.jsp?DIS=130323","references_en":null,"thisDefendant":[{"remark_zh":"","remark_en":"","references_zh":"","references_en":"","person":{"id":"4d6ca485-bdd0-45cf-b518-1c23570177f7","initial_zh":"杜","initial_en":null,"hide_name":true,"gender":"female","image_url":null,"case_person":[{"arrest_age":41,"occupation":{"type_zh":"健身中心東主","type_en":"健身中心東主"},"status":{"id":5,"type_zh":"當庭釋放","type_en":"當庭釋放"}},{"arrest_age":41,"occupation":{"type_zh":"健身中心東主","type_en":"健身中心東主"},"status":{"id":5,"type_zh":"當庭釋放","type_en":"當庭釋放"}},{"arrest_age":41,"occupation":{"type_zh":"健身中心東主","type_en":"健身中心東主"},"status":{"id":5,"type_zh":"當庭釋放","type_en":"當庭釋放"}},{"arrest_age":41,"occupation":{"type_zh":"健身中心東主","type_en":"健身中心東主"},"status":{"id":5,"type_zh":"當庭釋放","type_en":"當庭釋放"}}]},"total_sentence_zh":"","total_sentence_en":"","occupation":{"type_zh":"健身中心東主","type_en":"健身中心東主"},"status":{"id":5,"type_zh":"當庭釋放","type_en":"當庭釋放"},"charges":[{"id":"26dd377c-a364-4696-b8e4-a3285336a51d","content_zh":"於2019年7月28日在香港德輔道西近西邊街一帶，連同其他人參與暴動。","content_en":null,"charge":{"id":6,"name_zh":"暴動","name_en":null},"sentence_sp_zh":null,"sentence_sp_en":null,"sentence":null,"sentence_2":null,"sentence_3":null,"status":{"id":2,"type_zh":"罪名不成立","type_en":"罪名不成立"},"penalty":null,"penalty_2":null,"penalty_3":null,"arrest_location_zh":"德輔道西近西邊街一帶","arrest_location_en":null,"plead_guilty":"plead_no_guilty","start_date":"2019-07-28","remark_zh":"","remark_en":""},{"id":"60306f85-c4e0-47e9-b985-06c477c879c4","content_zh":"於2019年7月28日在西源里非以通訊事務管理局牌照行事，而管有各一部無線電收發機。","content_en":null,"charge":{"id":31,"name_zh":"無牌管有無線電通訊器具","name_en":null},"sentence_sp_zh":null,"sentence_sp_en":null,"sentence":{"id":8,"type_zh":"罰款（元）","type_en":"罰款（元）"},"sentence_2":null,"sentence_3":null,"status":{"id":1,"type_zh":"罪名成立","type_en":"罪名成立"},"penalty":10000,"penalty_2":null,"penalty_3":null,"arrest_location_zh":"西源里","arrest_location_en":null,"plead_guilty":"plead_no_guilty","start_date":"2019-07-28","remark_zh":"","remark_en":""}]}],"judge_2":null,"judge_3":null,"incident":{"id":8,"date":"2019-07-28","name_zh":"7.28 上環衝突","name_en":"","desc_zh":"網民發起在中環遮打花園集會，主題為追究警方在7.21上環清場時，無預警下對示威者開槍（橡膠子彈）、抗議7.21元朗白衣人無差別襲擊。集會開始不久，示威者在上環、金鐘、灣仔等地方聚集，入夜後發生激烈警民衝突。\n\n警方當晚頻密發射催淚彈，多次在地面及高位開槍，共使用408枚催淚彈、95發橡膠子彈、50發海綿彈及2枚布袋彈。\n\n這天49人被捕，其中44人被控暴動罪，也是警方在運動中首次大規模控以暴動。\n","desc_en":"","location":{"sub_district_zh":"上環","sub_district_en":"Sheung Wan"}},"progress":{"id":8,"type_zh":"結案","type_en":"結案"},"child_cases":[{"id":"ce9330a8-57c0-41e6-bdeb-7ed362e0c6f4","relation_name":{"id":2,"name_zh":"上訴","name_en":"Appeal"},"child":{"id":"ea3e6e9b-fd41-488a-a5af-1d6682f57915","case_num":"CASJ1/2020"}}],"parent_cases":[{"id":"c95b6c8d-c7d4-4b79-9f48-15c44d096900","relation_name":{"id":1,"name_zh":"轉介","name_en":"Referred"},"parent":{"id":"5bc56b24-8fb5-4e64-af25-48c7e9089703","case_num":"WKCC3437/2019"}}],"case_nums":["ESCC1843/2019","WKCC3437/2019","DCCC872/2019"]},{"id":"ea3e6e9b-fd41-488a-a5af-1d6682f57915","case_num":"CASJ1/2020","type":"appeal","subtype":"clarify_legal_opinion","next_hearing_date":null,"close_date":"2021-03-25","judge":{"name_zh":"潘兆初","name_en":"POON","title_zh":"高等法院首席法官","title_en":"Chief Judge of the High Court"},"remark_zh":"律政司要求上訴庭釐清「共同犯罪原則」（joint enterprise）可否套用在公眾集會的控罪。上訴結果不會影響原案三人的無罪裁決，但對日後同類案件影響深遠。","remark_en":null,"references_zh":"上訴庭判詞\nhttps://legalref.judiciary.hk/lrs/common/search/search_result_detail_frame.jsp?DIS=134508&QS=%28CASJ%7C1%2F2020%29&TP=JU","references_en":null,"thisDefendant":[{"remark_zh":"","remark_en":"","references_zh":"Title\nrecord['Reference (multiple entries)']","references_en":"Title\nrecord['Reference (multiple entries)']","person":{"id":"4d6ca485-bdd0-45cf-b518-1c23570177f7","initial_zh":"杜","initial_en":null,"hide_name":true,"gender":"female","image_url":null,"case_person":[{"arrest_age":41,"occupation":{"type_zh":"健身中心東主","type_en":"健身中心東主"},"status":{"id":5,"type_zh":"當庭釋放","type_en":"當庭釋放"}},{"arrest_age":41,"occupation":{"type_zh":"健身中心東主","type_en":"健身中心東主"},"status":{"id":5,"type_zh":"當庭釋放","type_en":"當庭釋放"}},{"arrest_age":41,"occupation":{"type_zh":"健身中心東主","type_en":"健身中心東主"},"status":{"id":5,"type_zh":"當庭釋放","type_en":"當庭釋放"}},{"arrest_age":41,"occupation":{"type_zh":"健身中心東主","type_en":"健身中心東主"},"status":{"id":5,"type_zh":"當庭釋放","type_en":"當庭釋放"}}]},"total_sentence_zh":"","total_sentence_en":"","occupation":{"type_zh":"健身中心東主","type_en":"健身中心東主"},"status":{"id":5,"type_zh":"當庭釋放","type_en":"當庭釋放"},"charges":[{"id":"a657f02d-7be1-4163-b998-6779b7885a3e","content_zh":"","content_en":"","charge":{"id":6,"name_zh":"暴動","name_en":null},"sentence_sp_zh":null,"sentence_sp_en":null,"sentence":null,"sentence_2":null,"sentence_3":null,"status":null,"penalty":null,"penalty_2":null,"penalty_3":null,"arrest_location_zh":null,"arrest_location_en":null,"plead_guilty":"pending_answer","start_date":null,"remark_zh":"","remark_en":""}]}],"judge_2":{"name_zh":"麥機智","name_en":"MACRAE, V-P","title_zh":"高等法院上訴法庭法官","title_en":"Justices of Appeal of the Court of Appeal of the High Court"},"judge_3":{"name_zh":"彭寶琴","name_en":"PANG","title_zh":"高等法院原訟法庭法官","title_en":"Judges of the Court of First Instance of the High Court"},"incident":{"id":8,"date":"2019-07-28","name_zh":"7.28 上環衝突","name_en":"","desc_zh":"網民發起在中環遮打花園集會，主題為追究警方在7.21上環清場時，無預警下對示威者開槍（橡膠子彈）、抗議7.21元朗白衣人無差別襲擊。集會開始不久，示威者在上環、金鐘、灣仔等地方聚集，入夜後發生激烈警民衝突。\n\n警方當晚頻密發射催淚彈，多次在地面及高位開槍，共使用408枚催淚彈、95發橡膠子彈、50發海綿彈及2枚布袋彈。\n\n這天49人被捕，其中44人被控暴動罪，也是警方在運動中首次大規模控以暴動。\n","desc_en":"","location":{"sub_district_zh":"上環","sub_district_en":"Sheung Wan"}},"progress":{"id":8,"type_zh":"結案","type_en":"結案"},"child_cases":[],"parent_cases":[{"id":"ce9330a8-57c0-41e6-bdeb-7ed362e0c6f4","relation_name":{"id":2,"name_zh":"上訴","name_en":"Appeal"},"parent":{"id":"c21241be-d81f-42f5-82cb-7f0feedc1ed2","case_num":"DCCC872/2019"}}],"case_nums":["CASJ1/2020"]}]],[[{"id":"ad09f70d-cc85-442c-9d40-fbe79e78dd28","case_num":"WKCC2680/2021","type":"original","subtype":null,"next_hearing_date":"2021-12-17","close_date":null,"judge":null,"remark_zh":null,"remark_en":null,"references_zh":"【「光城者」涉策劃襲擊】三男學生被控串謀恐怖活動　申保釋被拒　9.1再訊\nhttps://www.hkcnews.com/article/43158/%E6%B8%AF%E7%89%88%E5%9C%8B%E5%AE%89%E6%B3%95-43167/%E6%B8%AF%E7%89%88%E5%9C%8B%E5%AE%89%E6%B3%95?page=23","references_en":null,"thisDefendant":[{"remark_zh":"自2021年7月7日首提堂起被還柙。","remark_en":"","references_zh":"","references_en":"","person":{"id":"7b824ff8-0165-45f2-bcb6-b713836eac83","initial_zh":"*","initial_en":"","hide_name":true,"gender":"male","image_url":null,"case_person":[{"arrest_age":null,"occupation":{"type_zh":"學生","type_en":"學生"},"status":{"id":2,"type_zh":"還柙","type_en":"還柙"}}]},"total_sentence_zh":"","total_sentence_en":"","occupation":{"type_zh":"學生","type_en":"學生"},"status":{"id":2,"type_zh":"還柙","type_en":"還柙"},"charges":[{"id":"10678130-90d6-4497-8955-c43e956082ac","content_zh":"於2021年6月6日至2021年7月5日期間，在香港一同串謀及與其他人串謀，為脅迫中央人民政府或香港特別行政區政府或威嚇公眾以圖實現政治主張，組織、策劃、實施、參與實施或威脅意圖造成嚴重社會危害的恐怖活動，即爆炸、縱火、破壞交通工具或交通設施、或其他危險方法嚴重危害公眾健康或安全。","content_en":"","charge":{"id":70,"name_zh":"串謀恐怖活動","name_en":""},"sentence_sp_zh":null,"sentence_sp_en":null,"sentence":null,"sentence_2":null,"sentence_3":null,"status":null,"penalty":null,"penalty_2":null,"penalty_3":null,"arrest_location_zh":null,"arrest_location_en":null,"plead_guilty":"pending_answer","start_date":"2021-06-06","remark_zh":"","remark_en":""}]}],"judge_2":null,"judge_3":null,"incident":{"id":70,"date":"2021-07-05","name_zh":"「光城者」案","name_en":"","desc_zh":"組織「光城者」被指策劃7月上旬在過海隧道、鐵路、法庭、垃圾桶放置土製炸彈。\n\n警方國安處於7月5日在尖沙嘴一個賓館搗破製造土製炸彈的實驗室，並以恐怖活動罪拘捕5男4女，其中6人是中學生。案件中檢獲「微量」（trace amount）TATP原材料，警方無披露可製成炸彈數量。\n\n國安處先後起訴7名男女串謀恐怖活動罪，其後另再檢控7人串謀煽動他人實施顛覆國家政權罪，年紀最細為年僅15歲的中學生。","desc_en":"","location":null},"progress":{"id":1,"type_zh":"提堂","type_en":"提堂"},"child_cases":[],"parent_cases":[],"case_nums":["WKCC2680/2021"]}]],[[{"id":"9bc3a0a4-9caa-4894-964f-6ef85a154a25","case_num":"DCCC789/2020","type":"original","subtype":null,"next_hearing_date":null,"close_date":null,"judge":null,"remark_zh":null,"remark_en":null,"references_zh":null,"references_en":null,"thisDefendant":[{"remark_zh":"在2020年2月22日前往澳洲讀書，沒有回港記錄；法庭在2020年7月17日，充公其母親的十萬元擔保金。","remark_en":"","references_zh":"","references_en":"","person":{"id":"c10327ca-1ec0-4598-9a50-a4beaed275eb","initial_zh":"梁","initial_en":null,"hide_name":true,"gender":"male","image_url":null,"case_person":[{"arrest_age":24,"occupation":{"type_zh":"學生","type_en":"學生"},"status":{"id":4,"type_zh":"法庭批出拘捕令","type_en":"法庭批出拘捕令"}},{"arrest_age":24,"occupation":{"type_zh":"學生","type_en":"學生"},"status":{"id":4,"type_zh":"法庭批出拘捕令","type_en":"法庭批出拘捕令"}}]},"total_sentence_zh":"","total_sentence_en":"","occupation":{"type_zh":"學生","type_en":"學生"},"status":{"id":4,"type_zh":"法庭批出拘捕令","type_en":"法庭批出拘捕令"},"charges":[{"id":"7e61f11c-3664-488f-bb40-15f496db28b1","content_zh":"於2019年11月18日，在油麻地彌敦道近窩打老道交界，與其他人參與暴動。","content_en":"","charge":{"id":6,"name_zh":"暴動","name_en":null},"sentence_sp_zh":null,"sentence_sp_en":null,"sentence":null,"sentence_2":null,"sentence_3":null,"status":null,"penalty":null,"penalty_2":null,"penalty_3":null,"arrest_location_zh":"彌敦道近窩打老道交界","arrest_location_en":"","plead_guilty":"pending_answer","start_date":"2019-11-18","remark_zh":null,"remark_en":null}]}],"judge_2":null,"judge_3":null,"incident":{"id":38,"date":"2019-11-18","name_zh":"理大圍城﹒圍魏救趙","name_en":"","desc_zh":"【11月16日至29日 — 理大圍城13天】\n\n理大被圍封、被困者多次突圍失敗後，11月18日由早至晚，家長、人群、人鏈遍佈彌敦道，史無前例近10萬人在紅磡、尖沙咀、佐敦、油麻地、旺角等地，兵分多路試圖「圍魏救趙」。\n‍\n這夜的彌敦道，場面驚險，險象橫生，在油麻地碧街更出現人踩人慘劇。\n\n單是11月18日救理大行動，逾千人被捕，被控暴動罪其中242人在11月20日提堂，為反修例運動裡，單日最多被告提堂的案件。全港7個裁判法院中，共有6個法庭要晚上開庭處理，更有案件至翌日凌晨約1時才完成提訊，打破當時法庭最晚關門時間。","desc_en":"","location":null},"progress":{"id":1,"type_zh":"提堂","type_en":"提堂"},"child_cases":[],"parent_cases":[{"id":"eedf1926-64ad-4b56-8f73-b66c395efd8f","relation_name":{"id":1,"name_zh":"轉介","name_en":"Referred"},"parent":{"id":"985ad635-7842-405f-88e9-47afe9adc207","case_num":"KCCC2788/2019"}}],"case_nums":["KCCC2788/2019","DCCC789/2020"]}]],[[{"id":"249913b8-9cfc-4ad7-bf47-b25a3c814763","case_num":"DCCC28/2020","type":"original","subtype":null,"next_hearing_date":null,"close_date":"2021-03-31","judge":null,"remark_zh":null,"remark_en":null,"references_zh":"裁決理由書\nhttps://legalref.judiciary.hk/lrs/common/search/search_result_detail_frame.jsp?DIS=134483&QS=%28DCCC%7C814%2F2019%29&TP=RV","references_en":null,"thisDefendant":[{"remark_zh":"","remark_en":"","references_zh":"","references_en":"","person":{"id":"a9093047-6482-435b-b291-06283736bf79","initial_zh":"高","initial_en":null,"hide_name":true,"gender":"male","image_url":null,"case_person":[{"arrest_age":24,"occupation":{"type_zh":"廚師","type_en":"廚師"},"status":{"id":3,"type_zh":"服刑中","type_en":"服刑中"}},{"arrest_age":24,"occupation":{"type_zh":"廚師","type_en":"廚師"},"status":{"id":1,"type_zh":"保釋","type_en":"保釋"}}]},"total_sentence_zh":"","total_sentence_en":"","occupation":{"type_zh":"廚師","type_en":"廚師"},"status":{"id":3,"type_zh":"服刑中","type_en":"服刑中"},"charges":[{"id":"9d84230b-d3b5-4623-8c38-51d15ca79de3","content_zh":"於2019年8月13日，在香港國際機場一號客運大樓離境大堂外暢航路，連同其他身份不詳人士非法集結。","content_en":"","charge":{"id":7,"name_zh":"非法集結","name_en":null},"sentence_sp_zh":"量刑起點為監禁12個月，因機場犯案加刑兩個月，背景良好減刑一個月。","sentence_sp_en":null,"sentence":{"id":1,"type_zh":"監禁（日）","type_en":"監禁（日）"},"sentence_2":null,"sentence_3":null,"status":{"id":1,"type_zh":"罪名成立","type_en":"罪名成立"},"penalty":390,"penalty_2":null,"penalty_3":null,"arrest_location_zh":"機場一號客運大樓","arrest_location_en":"","plead_guilty":"plead_no_guilty","start_date":"2019-08-13","remark_zh":"在2020年1月21日，控方將公眾地方擾亂秩序罪修訂為非法集結罪。","remark_en":""}]}],"judge_2":null,"judge_3":null,"incident":{"id":11,"date":"2019-08-13","name_zh":"8.13 和你飛","name_en":"","desc_zh":"由8月9日起，網民一連多日在機場發起「萬人接機」行動，大批市民聚集在客運大樓接機大堂靜坐，並向抵港旅客派發解釋反送中運動的傳單。\n\n到13日，大批市民繼續在機場集會，晚上發生衝突，其中內地《環球時報》記者付國豪被懷疑身份，遭示威者包圍並用索帶將其手腳綁在行李車。\n","desc_en":"","location":{"sub_district_zh":"大嶼山","sub_district_en":"Lantau Island"}},"progress":{"id":8,"type_zh":"結案","type_en":"結案"},"child_cases":[],"parent_cases":[{"id":"b8b47c2f-a1f1-437d-9589-c9fd8bf0cd78","relation_name":{"id":1,"name_zh":"轉介","name_en":"Referred"},"parent":{"id":"7b31989e-abaa-4ef6-bc88-c436670497c2","case_num":"ESCC2752/2019"}}],"case_nums":["ESCC2752/2019","DCCC28/2020"]}]]]