[[{"id":"7d4b51a6-4f5f-46ac-a7e6-43f5f6485d75","case_num":"DCCC947/2020","type":"original","subtype":null,"next_hearing_date":null,"close_date":null,"judge":null,"remark_zh":null,"remark_en":null,"references_zh":null,"references_en":null,"thisDefendant":[{"remark_zh":"","remark_en":"","references_zh":"","references_en":"","person":{"id":"20538d4f-1de6-4c96-86b0-1c9d4c7d95f1","initial_zh":"楊","initial_en":"","hide_name":true,"gender":"male","image_url":null,"case_person":[{"arrest_age":null,"occupation":{"type_zh":"無業","type_en":"無業"},"status":{"id":1,"type_zh":"保釋","type_en":"保釋"}},{"arrest_age":null,"occupation":{"type_zh":"無業","type_en":"無業"},"status":{"id":1,"type_zh":"保釋","type_en":"保釋"}}]},"total_sentence_zh":"","total_sentence_en":"","occupation":{"type_zh":"無業","type_en":"無業"},"status":{"id":1,"type_zh":"保釋","type_en":"保釋"},"charges":[{"id":"2cb1066a-9b8a-4a43-be4f-2f43bf8a39e3","content_zh":"於2020年1月19日，在中環遮打花園及長江中心一帶，與不知名人士參與暴動。","content_en":"","charge":{"id":6,"name_zh":"暴動","name_en":null},"sentence_sp_zh":null,"sentence_sp_en":null,"sentence":null,"sentence_2":null,"sentence_3":null,"status":null,"penalty":null,"penalty_2":null,"penalty_3":null,"arrest_location_zh":"遮打花園及長江中心一帶","arrest_location_en":null,"plead_guilty":"pending_answer","start_date":"2020-01-19","remark_zh":"","remark_en":""},{"id":"d95315e1-eb9a-492d-bb26-1a69ab27d191","content_zh":"於2020年1月19日，在中環長江中心外，串謀非法及惡意導致高級督察34135、警署警長54996、女警長 57216、警員14804，及一名不知名人士身體受嚴重傷害。","content_en":"","charge":{"id":12,"name_zh":"串謀有意圖傷人","name_en":null},"sentence_sp_zh":null,"sentence_sp_en":null,"sentence":null,"sentence_2":null,"sentence_3":null,"status":null,"penalty":null,"penalty_2":null,"penalty_3":null,"arrest_location_zh":"長江中心外","arrest_location_en":null,"plead_guilty":"pending_answer","start_date":"2020-01-19","remark_zh":"","remark_en":""}]}],"judge_2":null,"judge_3":null,"incident":{"id":61,"date":"2020-01-19","name_zh":"1.19 「天下制裁」集會","name_en":"","desc_zh":"民間集會團隊在中環遮打道及遮打花園舉行「天下制裁」集會，促請政府立即推行民主政改，否則呼籲其他國家制裁香港官員及警方高層。\n\n不過，集會在進行約一個半小時後被警方腰斬，事件演變成激烈警民衝突，事後大會發言人劉頴匡被捕。","desc_en":"","location":null},"progress":{"id":1,"type_zh":"提堂","type_en":"提堂"},"child_cases":[],"parent_cases":[{"id":"eed64174-76bf-4abb-9d24-ab6922a50cbf","relation_name":{"id":1,"name_zh":"轉介","name_en":"Referred"},"parent":{"id":"1a5580ea-16b8-432a-8732-f487fab60864","case_num":"ESCC708/2020"}}],"case_nums":["ESCC708/2020","DCCC947/2020"]}]]