[[{"id":"628de3f6-e76c-4efb-8cad-e809c0a2fc73","case_num":"DCCC113/2021","type":"original","subtype":null,"next_hearing_date":"2023-06-05","close_date":null,"judge":null,"remark_zh":null,"remark_en":null,"references_zh":null,"references_en":null,"thisDefendant":[{"remark_zh":"","remark_en":"","references_zh":"","references_en":"","person":{"id":"56eedf71-02ba-4680-a6a4-9ee7fbc85e72","initial_zh":"郭","initial_en":null,"hide_name":true,"gender":"female","image_url":null,"case_person":[{"arrest_age":20,"occupation":{"type_zh":"無業","type_en":"無業"},"status":{"id":1,"type_zh":"保釋","type_en":"保釋"}},{"arrest_age":20,"occupation":{"type_zh":"無業","type_en":"無業"},"status":{"id":1,"type_zh":"保釋","type_en":"保釋"}},{"arrest_age":20,"occupation":{"type_zh":"無業","type_en":"無業"},"status":null}]},"total_sentence_zh":"","total_sentence_en":"","occupation":{"type_zh":"無業","type_en":"無業"},"status":{"id":1,"type_zh":"保釋","type_en":"保釋"},"charges":[{"id":"0493a6e2-1b98-4f02-b51b-b4f759520857","content_zh":"於2019年9月29日，在港島金鐘道一帶，連同其他不知名人士參與暴動。","content_en":"","charge":{"id":6,"name_zh":"暴動","name_en":null},"sentence_sp_zh":null,"sentence_sp_en":null,"sentence":null,"sentence_2":null,"sentence_3":null,"status":null,"penalty":null,"penalty_2":null,"penalty_3":null,"arrest_location_zh":"金鐘道一帶","arrest_location_en":"","plead_guilty":"pending_answer","start_date":"2019-09-29","remark_zh":"","remark_en":""}]}],"judge_2":null,"judge_3":null,"incident":{"id":20,"date":"2019-09-29","name_zh":"9.29 全球反極權大遊行","name_en":"","desc_zh":"網民發起下午在港島區舉行「全球反極權大遊行」，警方及示威者在金鐘、灣仔一帶爆發衝突。全日共146人被捕，其中96人被控暴動罪。\n\n同日，印尼女記者Veby Mega Indah懷疑被警方發射的布袋彈擊中右眼失明。","desc_en":"","location":{"sub_district_zh":"金鐘","sub_district_en":"Admiralty"}},"progress":{"id":4,"type_zh":"審訊","type_en":"審訊"},"child_cases":[],"parent_cases":[{"id":"24457178-1bc7-441b-97b1-4b7f9d2aec64","relation_name":{"id":1,"name_zh":"轉介","name_en":"Referred"},"parent":{"id":"109a15ff-7c12-4076-a630-ab02f145ea4d","case_num":"DCCC294/2020"}}],"case_nums":["WKCC3792/2019","DCCC294/2020","DCCC113/2021"]}]]