[[{"id":"d1821807-6949-47ef-aa28-6a66ed14e10f","case_num":"DCCC877/2020","type":"original","subtype":null,"next_hearing_date":null,"close_date":null,"judge":null,"remark_zh":null,"remark_en":null,"references_zh":null,"references_en":null,"thisDefendant":[{"remark_zh":"","remark_en":"","references_zh":"Title\nrecord['Reference (multiple entries)']","references_en":"Title\nrecord['Reference (multiple entries)']","person":{"id":"c4fc1d46-d7fb-4023-af06-6c11bbe42e10","initial_zh":"梁","initial_en":null,"hide_name":false,"gender":"male","image_url":null,"case_person":[{"arrest_age":35,"occupation":{"type_zh":"支聯會前常委","type_en":"支聯會前常委"},"status":{"id":1,"type_zh":"保釋","type_en":"保釋"}},{"arrest_age":35,"occupation":{"type_zh":"支聯會前常委","type_en":"支聯會前常委"},"status":{"id":1,"type_zh":"保釋","type_en":"保釋"}},{"arrest_age":35,"occupation":{"type_zh":"支聯會前常委","type_en":"支聯會前常委"},"status":{"id":1,"type_zh":"保釋","type_en":"保釋"}},{"arrest_age":35,"occupation":{"type_zh":"支聯會前常委","type_en":"支聯會前常委"},"status":{"id":1,"type_zh":"保釋","type_en":"保釋"}},{"arrest_age":null,"occupation":{"type_zh":"葵青區區議員","type_en":""},"status":{"id":2,"type_zh":"還柙","type_en":"還柙"}}]},"total_sentence_zh":"","total_sentence_en":"","occupation":{"type_zh":"支聯會前常委","type_en":"支聯會前常委"},"status":{"id":1,"type_zh":"保釋","type_en":"保釋"},"charges":[{"id":"a568f1ec-9cdc-44c3-a050-6cb501e8fe57","content_zh":"於2020年6月4日，在維多利亞公園噴水池外，非法煽惑其他身分不詳的人在無合法權限或無合理辯解的情況下，明知而參與一個未經批准集結。","content_en":null,"charge":{"id":33,"name_zh":"煽惑未經批准集結","name_en":null},"sentence_sp_zh":null,"sentence_sp_en":null,"sentence":null,"sentence_2":null,"sentence_3":null,"status":null,"penalty":null,"penalty_2":null,"penalty_3":null,"arrest_location_zh":"維多利亞公園噴水池外","arrest_location_en":null,"plead_guilty":"pending_answer","start_date":"2020-06-04","remark_zh":"","remark_en":""}]}],"judge_2":null,"judge_3":null,"incident":{"id":44,"date":"2020-06-04","name_zh":"六四31周年﹒維園悼念晚會","name_en":"","desc_zh":"六四事件31周年，警方以疫情為由，首次禁止支聯會在維園舉行六四燭光晚會，但當晚仍有大批市民自發到維園悼念。\n\n事後26名民主派人士，包括支聯會主席李卓人及11名常委、前香港眾志秘書長黃之鋒、壹傳媒創辦人黎智英等，被控煽惑他人明知而參與非法集結、明知而參與未經批准集結等罪。\n\n前香港眾志主席羅冠聰及前民間外交網絡發言人張崑陽，同為案件被告，但二人經已離港未有應訊，法庭批出拘捕令。","desc_en":"","location":{"sub_district_zh":"銅鑼灣","sub_district_en":"Causeway Bay"}},"progress":{"id":1,"type_zh":"提堂","type_en":"提堂"},"child_cases":[],"parent_cases":[{"id":"b27965c6-761a-4c0a-9f40-69e5c29c34fa","relation_name":{"id":1,"name_zh":"轉介","name_en":"Referred"},"parent":{"id":"622246fd-e09e-4b0f-907a-173b963f4420","case_num":"ESS13523/2020"}}],"case_nums":["ESS13523/2020","DCCC877/2020"]}],[{"id":"873fd5a7-8bcc-4581-9fbc-4b47fbada413","case_num":"WKCC3633/2021","type":"original","subtype":null,"next_hearing_date":"2021-10-21","close_date":null,"judge":null,"remark_zh":null,"remark_en":null,"references_zh":null,"references_en":null,"thisDefendant":[{"remark_zh":"由2021年9月10日首提堂起遭還柙。","remark_en":"","references_zh":"","references_en":"","person":{"id":"c4fc1d46-d7fb-4023-af06-6c11bbe42e10","initial_zh":"梁","initial_en":null,"hide_name":false,"gender":"male","image_url":null,"case_person":[{"arrest_age":35,"occupation":{"type_zh":"支聯會前常委","type_en":"支聯會前常委"},"status":{"id":1,"type_zh":"保釋","type_en":"保釋"}},{"arrest_age":35,"occupation":{"type_zh":"支聯會前常委","type_en":"支聯會前常委"},"status":{"id":1,"type_zh":"保釋","type_en":"保釋"}},{"arrest_age":35,"occupation":{"type_zh":"支聯會前常委","type_en":"支聯會前常委"},"status":{"id":1,"type_zh":"保釋","type_en":"保釋"}},{"arrest_age":35,"occupation":{"type_zh":"支聯會前常委","type_en":"支聯會前常委"},"status":{"id":1,"type_zh":"保釋","type_en":"保釋"}},{"arrest_age":null,"occupation":{"type_zh":"葵青區區議員","type_en":""},"status":{"id":2,"type_zh":"還柙","type_en":"還柙"}}]},"total_sentence_zh":"","total_sentence_en":"","occupation":{"type_zh":"葵青區區議員","type_en":""},"status":{"id":2,"type_zh":"還柙","type_en":"還柙"},"charges":[{"id":"cb1f2976-4878-42de-982c-a1d6401bfeb5","content_zh":"於2021年9月8日，作為「香港市民支援愛國民主活動聯合會」在香港的幹事或在香港管理或協助管理該組織的人士，並已獲根據《港區國安法第 43 條實施細則》附表 5 第3(1)(b) 條送達通知，而沒有遵從該通知的規定。","content_en":"","charge":{"id":68,"name_zh":"沒有遵從通知規定提供資料","name_en":""},"sentence_sp_zh":null,"sentence_sp_en":null,"sentence":null,"sentence_2":null,"sentence_3":null,"status":null,"penalty":null,"penalty_2":null,"penalty_3":null,"arrest_location_zh":null,"arrest_location_en":null,"plead_guilty":"pending_answer","start_date":"2021-09-08","remark_zh":"","remark_en":""}]}],"judge_2":null,"judge_3":null,"incident":null,"progress":{"id":1,"type_zh":"提堂","type_en":"提堂"},"child_cases":[],"parent_cases":[],"case_nums":["WKCC3633/2021"]}],[{"id":"6d09e907-fe94-48f0-9c03-71c50a92ac79","case_num":"DCCC878/2020","type":"original","subtype":null,"next_hearing_date":null,"close_date":null,"judge":{"name_zh":"陳廣池","name_en":"Stanley CHAN","title_zh":"區域法院法官","title_en":"District Judges"},"remark_zh":null,"remark_en":null,"references_zh":null,"references_en":null,"thisDefendant":[{"remark_zh":"","remark_en":"","references_zh":"Title\nrecord['Reference (multiple entries)']","references_en":"Title\nrecord['Reference (multiple entries)']","person":{"id":"c4fc1d46-d7fb-4023-af06-6c11bbe42e10","initial_zh":"梁","initial_en":null,"hide_name":false,"gender":"male","image_url":null,"case_person":[{"arrest_age":35,"occupation":{"type_zh":"支聯會前常委","type_en":"支聯會前常委"},"status":{"id":1,"type_zh":"保釋","type_en":"保釋"}},{"arrest_age":35,"occupation":{"type_zh":"支聯會前常委","type_en":"支聯會前常委"},"status":{"id":1,"type_zh":"保釋","type_en":"保釋"}},{"arrest_age":35,"occupation":{"type_zh":"支聯會前常委","type_en":"支聯會前常委"},"status":{"id":1,"type_zh":"保釋","type_en":"保釋"}},{"arrest_age":35,"occupation":{"type_zh":"支聯會前常委","type_en":"支聯會前常委"},"status":{"id":1,"type_zh":"保釋","type_en":"保釋"}},{"arrest_age":null,"occupation":{"type_zh":"葵青區區議員","type_en":""},"status":{"id":2,"type_zh":"還柙","type_en":"還柙"}}]},"total_sentence_zh":"","total_sentence_en":"","occupation":{"type_zh":"支聯會前常委","type_en":"支聯會前常委"},"status":{"id":1,"type_zh":"保釋","type_en":"保釋"},"charges":[{"id":"4f71c94b-14fe-42be-a6ac-137c2916646a","content_zh":"於2020年6月4日，在維多利亞公園，連同其他不知名人士參與一場未經批准集結。","content_en":null,"charge":{"id":34,"name_zh":"明知而參與未經批准集結","name_en":null},"sentence_sp_zh":null,"sentence_sp_en":null,"sentence":null,"sentence_2":null,"sentence_3":null,"status":null,"penalty":null,"penalty_2":null,"penalty_3":null,"arrest_location_zh":"維多利亞公園","arrest_location_en":null,"plead_guilty":"pending_answer","start_date":"2020-06-04","remark_zh":"","remark_en":""}]}],"judge_2":null,"judge_3":null,"incident":{"id":44,"date":"2020-06-04","name_zh":"六四31周年﹒維園悼念晚會","name_en":"","desc_zh":"六四事件31周年，警方以疫情為由，首次禁止支聯會在維園舉行六四燭光晚會，但當晚仍有大批市民自發到維園悼念。\n\n事後26名民主派人士，包括支聯會主席李卓人及11名常委、前香港眾志秘書長黃之鋒、壹傳媒創辦人黎智英等，被控煽惑他人明知而參與非法集結、明知而參與未經批准集結等罪。\n\n前香港眾志主席羅冠聰及前民間外交網絡發言人張崑陽，同為案件被告，但二人經已離港未有應訊，法庭批出拘捕令。","desc_en":"","location":{"sub_district_zh":"銅鑼灣","sub_district_en":"Causeway Bay"}},"progress":{"id":1,"type_zh":"提堂","type_en":"提堂"},"child_cases":[],"parent_cases":[{"id":"f148d958-fc81-4b85-a66b-24ca2e6254e0","relation_name":{"id":1,"name_zh":"轉介","name_en":"Referred"},"parent":{"id":"8a64dcb6-607c-4ac8-aff9-55ba8d518eab","case_num":"WKS8797/2020"}}],"case_nums":["WKS8797/2020","DCCC878/2020"]}]]