{"id":49,"date":"2019-11-11","name_zh":"中大保衛戰﹒第一天","name_en":"","defendants":[{"person":{"id":"c404e9b5-0d23-4d61-9183-fcccb63b8c20","initial_zh":"高","initial_en":null,"hide_name":true,"gender":"male","image_url":null,"case_person":[{"arrest_age":21,"occupation":{"type_zh":"學生","type_en":"學生"},"status":{"id":2,"type_zh":"還柙","type_en":"還柙"}},{"arrest_age":21,"occupation":null,"status":null}]},"status":{"id":2,"type_zh":"還柙","type_en":"還柙"}},{"person":{"id":"18ac6b49-7d0d-4a04-88f0-b3416cf7038e","initial_zh":"許","initial_en":null,"hide_name":true,"gender":"male","image_url":null,"case_person":[{"arrest_age":20,"occupation":{"type_zh":"學生","type_en":"學生"},"status":{"id":2,"type_zh":"還柙","type_en":"還柙"}},{"arrest_age":20,"occupation":null,"status":null}]},"status":{"id":2,"type_zh":"還柙","type_en":"還柙"}},{"person":{"id":"99f35e89-0391-4b27-a5ae-8701ce5f56da","initial_zh":"劉","initial_en":null,"hide_name":true,"gender":"male","image_url":null,"case_person":[{"arrest_age":21,"occupation":{"type_zh":"學生","type_en":"學生"},"status":{"id":2,"type_zh":"還柙","type_en":"還柙"}},{"arrest_age":21,"occupation":null,"status":null}]},"status":{"id":2,"type_zh":"還柙","type_en":"還柙"}},{"person":{"id":"d98f149d-01ee-41a1-9ac4-954192fe9e26","initial_zh":"符","initial_en":null,"hide_name":true,"gender":"female","image_url":null,"case_person":[{"arrest_age":null,"occupation":{"type_zh":"學生","type_en":"學生"},"status":{"id":2,"type_zh":"還柙","type_en":"還柙"}},{"arrest_age":21,"occupation":{"type_zh":"學生","type_en":"學生"},"status":{"id":2,"type_zh":"還柙","type_en":"還柙"}},{"arrest_age":21,"occupation":null,"status":null}]},"status":{"id":2,"type_zh":"還柙","type_en":"還柙"}},{"person":{"id":"22bf2920-ce52-4a0f-ad57-d95858c5993b","initial_zh":"陳","initial_en":null,"hide_name":true,"gender":"male","image_url":null,"case_person":[{"arrest_age":18,"occupation":{"type_zh":"學生","type_en":"學生"},"status":{"id":2,"type_zh":"還柙","type_en":"還柙"}},{"arrest_age":18,"occupation":null,"status":null}]},"status":{"id":2,"type_zh":"還柙","type_en":"還柙"}}]}